{
  "rodada_atual": 40,
  "jogos_processados": 380,
  "entradas": [
    {
      "home": "Chievo",
      "away": "Juventus",
      "b365h": 13.0,
      "b365a": 1.25,
      "xgh": 3.04,
      "xga": 1.07,
      "dxg": "FH",
      "odd_home_calc": 1.47,
      "odd_away_calc": 10.04,
      "entrada": "HOME",
      "fthg": 2.0,
      "ftag": 3.0,
      "lp": -1
    },
    {
      "home": "Lazio",
      "away": "Napoli",
      "b365h": 2.8,
      "b365a": 2.5,
      "xgh": 0.66,
      "xga": 0.96,
      "dxg": "EQ",
      "odd_home_calc": 4.13,
      "odd_away_calc": 2.43,
      "entrada": "AWAY",
      "fthg": 1.0,
      "ftag": 2.0,
      "lp": 1.5
    },
    {
      "home": "Bologna",
      "away": "Spal",
      "b365h": 2.25,
      "b365a": 3.4,
      "xgh": 1.1,
      "xga": 1.19,
      "dxg": "EQ",
      "odd_home_calc": 2.99,
      "odd_away_calc": 2.64,
      "entrada": "AWAY",
      "fthg": 0.0,
      "ftag": 1.0,
      "lp": 2.4
    },
    {
      "home": "Empoli",
      "away": "Cagliari",
      "b365h": 2.14,
      "b365a": 3.6,
      "xgh": 0.88,
      "xga": 0.69,
      "dxg": "EQ",
      "odd_home_calc": 2.65,
      "odd_away_calc": 3.72,
      "entrada": "HOME",
      "fthg": 2.0,
      "ftag": 0.0,
      "lp": 1.14
    },
    {
      "home": "Parma",
      "away": "Udinese",
      "b365h": 2.45,
      "b365a": 2.9,
      "xgh": 0.67,
      "xga": 0.83,
      "dxg": "EQ",
      "odd_home_calc": 3.68,
      "odd_away_calc": 2.76,
      "entrada": "HOME",
      "fthg": 2.0,
      "ftag": 2.0,
      "lp": -1
    },
    {
      "home": "Torino",
      "away": "Roma",
      "b365h": 3.5,
      "b365a": 2.1,
      "xgh": 1.44,
      "xga": 1.19,
      "dxg": "EQ",
      "odd_home_calc": 2.36,
      "odd_away_calc": 3.21,
      "entrada": "HOME",
      "fthg": 0.0,
      "ftag": 1.0,
      "lp": -1
    },
    {
      "home": "Sampdoria",
      "away": "Fiorentina",
      "b365h": 2.87,
      "b365a": 2.54,
      "xgh": 1.23,
      "xga": 0.87,
      "dxg": "LH",
      "odd_home_calc": 2.25,
      "odd_away_calc": 3.83,
      "entrada": "HOME",
      "fthg": 1.0,
      "ftag": 1.0,
      "lp": -1
    },
    {
      "home": "Milan",
      "away": "Genoa",
      "b365h": 1.44,
      "b365a": 7.5,
      "xgh": 1.2,
      "xga": 0.7,
      "dxg": "LH",
      "odd_home_calc": 2.09,
      "odd_away_calc": 4.62,
      "entrada": "AWAY",
      "fthg": 2.0,
      "ftag": 1.0,
      "lp": -1
    },
    {
      "home": "Udinese",
      "away": "Sampdoria",
      "b365h": 2.4,
      "b365a": 3.1,
      "xgh": 0.75,
      "xga": 0.65,
      "dxg": "EQ",
      "odd_home_calc": 2.98,
      "odd_away_calc": 3.55,
      "entrada": "HOME",
      "fthg": 1.0,
      "ftag": 0.0,
      "lp": 1.4
    },
    {
      "home": "Spal",
      "away": "Parma",
      "b365h": 2.04,
      "b365a": 3.8,
      "xgh": 1.4,
      "xga": 0.58,
      "dxg": "LH",
      "odd_home_calc": 1.76,
      "odd_away_calc": 6.49,
      "entrada": "HOME",
      "fthg": 1.0,
      "ftag": 0.0,
      "lp": 1.04
    },
    {
      "home": "Inter",
      "away": "Torino",
      "b365h": 1.5,
      "b365a": 7.0,
      "xgh": 1.69,
      "xga": 1.58,
      "dxg": "EQ",
      "odd_home_calc": 2.51,
      "odd_away_calc": 2.8,
      "entrada": "AWAY",
      "fthg": 2.0,
      "ftag": 2.0,
      "lp": -1
    },
    {
      "home": "Frosinone",
      "away": "Bologna",
      "b365h": 3.3,
      "b365a": 2.4,
      "xgh": 0.81,
      "xga": 0.21,
      "dxg": "LH",
      "odd_home_calc": 2.07,
      "odd_away_calc": 10.99,
      "entrada": "HOME",
      "fthg": 0.0,
      "ftag": 0.0,
      "lp": -1
    },
    {
      "home": "Cagliari",
      "away": "Sassuolo",
      "b365h": 2.45,
      "b365a": 2.9,
      "xgh": 2.07,
      "xga": 0.99,
      "dxg": "FH",
      "odd_home_calc": 1.66,
      "odd_away_calc": 5.8,
      "entrada": "HOME",
      "fthg": 2.0,
      "ftag": 2.0,
      "lp": -1
    },
    {
      "home": "Genoa",
      "away": "Empoli",
      "b365h": 1.95,
      "b365a": 4.0,
      "xgh": 1.53,
      "xga": 0.35,
      "dxg": "FH",
      "odd_home_calc": 1.49,
      "odd_away_calc": 12.4,
      "entrada": "HOME",
      "fthg": 2.0,
      "ftag": 1.0,
      "lp": 0.95
    },
    {
      "home": "Roma",
      "away": "Atalanta",
      "b365h": 1.72,
      "b365a": 5.0,
      "xgh": 1.31,
      "xga": 0.84,
      "dxg": "LH",
      "odd_home_calc": 2.12,
      "odd_away_calc": 4.15,
      "entrada": "AWAY",
      "fthg": 3.0,
      "ftag": 3.0,
      "lp": -1
    },
    {
      "home": "Juventus",
      "away": "Napoli",
      "b365h": 1.8,
      "b365a": 4.75,
      "xgh": 1.52,
      "xga": 0.11,
      "dxg": "FH",
      "odd_home_calc": 1.35,
      "odd_away_calc": 20,
      "entrada": "HOME",
      "fthg": 3.0,
      "ftag": 1.0,
      "lp": 0.8
    },
    {
      "home": "Lazio",
      "away": "Milan",
      "b365h": 1.85,
      "b365a": 4.2,
      "xgh": 1.47,
      "xga": 1.27,
      "dxg": "EQ",
      "odd_home_calc": 2.41,
      "odd_away_calc": 3.08,
      "entrada": "AWAY",
      "fthg": 1.0,
      "ftag": 1.0,
      "lp": -1
    },
    {
      "home": "Sassuolo",
      "away": "Genoa",
      "b365h": 2.1,
      "b365a": 3.75,
      "xgh": 0.6,
      "xga": 1.2,
      "dxg": "LA",
      "odd_home_calc": 5.43,
      "odd_away_calc": 1.97,
      "entrada": "AWAY",
      "fthg": 5.0,
      "ftag": 3.0,
      "lp": -1
    },
    {
      "home": "Torino",
      "away": "Spal",
      "b365h": 1.66,
      "b365a": 5.5,
      "xgh": 0.62,
      "xga": 0.95,
      "dxg": "LA",
      "odd_home_calc": 4.37,
      "odd_away_calc": 2.38,
      "entrada": "AWAY",
      "fthg": 1.0,
      "ftag": 0.0,
      "lp": -1
    },
    {
      "home": "Sampdoria",
      "away": "Napoli",
      "b365h": 6.5,
      "b365a": 1.53,
      "xgh": 2.02,
      "xga": 1.09,
      "dxg": "LH",
      "odd_home_calc": 1.75,
      "odd_away_calc": 5.06,
      "entrada": "HOME",
      "fthg": 3.0,
      "ftag": 0.0,
      "lp": 5.5
    },
    {
      "home": "Chievo",
      "away": "Empoli",
      "b365h": 2.3,
      "b365a": 3.3,
      "xgh": 1.17,
      "xga": 0.98,
      "dxg": "EQ",
      "odd_home_calc": 2.51,
      "odd_away_calc": 3.27,
      "entrada": "HOME",
      "fthg": 0.0,
      "ftag": 0.0,
      "lp": -1
    },
    {
      "home": "Fiorentina",
      "away": "Udinese",
      "b365h": 1.57,
      "b365a": 6.0,
      "xgh": 1.75,
      "xga": 0.29,
      "dxg": "FH",
      "odd_home_calc": 1.37,
      "odd_away_calc": 18.31,
      "entrada": "HOME",
      "fthg": 1.0,
      "ftag": 0.0,
      "lp": 0.57
    },
    {
      "home": "Atalanta",
      "away": "Cagliari",
      "b365h": 1.55,
      "b365a": 6.0,
      "xgh": 0.99,
      "xga": 1.24,
      "dxg": "EQ",
      "odd_home_calc": 3.4,
      "odd_away_calc": 2.39,
      "entrada": "AWAY",
      "fthg": 0.0,
      "ftag": 1.0,
      "lp": 5.0
    },
    {
      "home": "Bologna",
      "away": "Roma",
      "b365h": 5.5,
      "b365a": 1.66,
      "xgh": 0.54,
      "xga": 0.95,
      "dxg": "LA",
      "odd_home_calc": 4.97,
      "odd_away_calc": 2.27,
      "entrada": "HOME",
      "fthg": 2.0,
      "ftag": 0.0,
      "lp": 4.5
    },
    {
      "home": "Inter",
      "away": "Milan",
      "b365h": 2.45,
      "b365a": 3.0,
      "xgh": 1.05,
      "xga": 1.74,
      "dxg": "LA",
      "odd_home_calc": 4.41,
      "odd_away_calc": 1.9,
      "entrada": "AWAY",
      "fthg": 1.0,
      "ftag": 0.0,
      "lp": -1
    },
    {
      "home": "Udinese",
      "away": "Torino",
      "b365h": 2.9,
      "b365a": 2.5,
      "xgh": 1.05,
      "xga": 1.17,
      "dxg": "EQ",
      "odd_home_calc": 3.08,
      "odd_away_calc": 2.6,
      "entrada": "AWAY",
      "fthg": 1.0,
      "ftag": 1.0,
      "lp": -1
    },
    {
      "home": "Juventus",
      "away": "Sassuolo",
      "b365h": 1.2,
      "b365a": 13.0,
      "xgh": 2.19,
      "xga": 0.99,
      "dxg": "FH",
      "odd_home_calc": 1.61,
      "odd_away_calc": 6.3,
      "entrada": "AWAY",
      "fthg": 2.0,
      "ftag": 1.0,
      "lp": -1
    },
    {
      "home": "Empoli",
      "away": "Lazio",
      "b365h": 5.0,
      "b365a": 1.7,
      "xgh": 1.42,
      "xga": 1.11,
      "dxg": "LH",
      "odd_home_calc": 2.29,
      "odd_away_calc": 3.39,
      "entrada": "HOME",
      "fthg": 0.0,
      "ftag": 1.0,
      "lp": -1
    },
    {
      "home": "Cagliari",
      "away": "Milan",
      "b365h": 5.0,
      "b365a": 1.75,
      "xgh": 1.45,
      "xga": 1.3,
      "dxg": "EQ",
      "odd_home_calc": 2.47,
      "odd_away_calc": 2.99,
      "entrada": "HOME",
      "fthg": 1.0,
      "ftag": 1.0,
      "lp": -1
    },
    {
      "home": "Genoa",
      "away": "Bologna",
      "b365h": 1.9,
      "b365a": 4.5,
      "xgh": 1.21,
      "xga": 0.8,
      "dxg": "LH",
      "odd_home_calc": 2.19,
      "odd_away_calc": 4.09,
      "entrada": "AWAY",
      "fthg": 1.0,
      "ftag": 0.0,
      "lp": -1
    },
    {
      "home": "Spal",
      "away": "Atalanta",
      "b365h": 4.0,
      "b365a": 1.95,
      "xgh": 0.97,
      "xga": 2.39,
      "dxg": "FA",
      "odd_home_calc": 7.37,
      "odd_away_calc": 1.53,
      "entrada": "AWAY",
      "fthg": 2.0,
      "ftag": 0.0,
      "lp": -1
    },
    {
      "home": "Parma",
      "away": "Cagliari",
      "b365h": 2.4,
      "b365a": 3.1,
      "xgh": 0.9,
      "xga": 0.73,
      "dxg": "EQ",
      "odd_home_calc": 2.68,
      "odd_away_calc": 3.58,
      "entrada": "HOME",
      "fthg": 2.0,
      "ftag": 0.0,
      "lp": 1.4
    },
    {
      "home": "Sampdoria",
      "away": "Inter",
      "b365h": 4.33,
      "b365a": 1.8,
      "xgh": 0.7,
      "xga": 2.66,
      "dxg": "FA",
      "odd_home_calc": 13.49,
      "odd_away_calc": 1.36,
      "entrada": "AWAY",
      "fthg": 0.0,
      "ftag": 1.0,
      "lp": 0.8
    },
    {
      "home": "Milan",
      "away": "Atalanta",
      "b365h": 2.04,
      "b365a": 3.6,
      "xgh": 1.68,
      "xga": 0.8,
      "dxg": "LH",
      "odd_home_calc": 1.74,
      "odd_away_calc": 5.64,
      "entrada": "HOME",
      "fthg": 2.0,
      "ftag": 2.0,
      "lp": -1
    },
    {
      "home": "Lazio",
      "away": "Genoa",
      "b365h": 1.44,
      "b365a": 8.0,
      "xgh": 1.33,
      "xga": 0.72,
      "dxg": "LH",
      "odd_home_calc": 1.96,
      "odd_away_calc": 4.96,
      "entrada": "AWAY",
      "fthg": 4.0,
      "ftag": 1.0,
      "lp": -1
    },
    {
      "home": "Chievo",
      "away": "Udinese",
      "b365h": 3.0,
      "b365a": 2.5,
      "xgh": 0.56,
      "xga": 2.14,
      "dxg": "FA",
      "odd_home_calc": 12.03,
      "odd_away_calc": 1.39,
      "entrada": "AWAY",
      "fthg": 0.0,
      "ftag": 2.0,
      "lp": 1.5
    },
    {
      "home": "Bologna",
      "away": "Roma",
      "b365h": 5.5,
      "b365a": 1.66,
      "xgh": 0.75,
      "xga": 0.83,
      "dxg": "EQ",
      "odd_home_calc": 3.34,
      "odd_away_calc": 2.9,
      "entrada": "HOME",
      "fthg": 2.0,
      "ftag": 0.0,
      "lp": 4.5
    },
    {
      "home": "Empoli",
      "away": "Sassuolo",
      "b365h": 2.7,
      "b365a": 2.6,
      "xgh": 1.58,
      "xga": 1.77,
      "dxg": "EQ",
      "odd_home_calc": 2.93,
      "odd_away_calc": 2.4,
      "entrada": "AWAY",
      "fthg": 3.0,
      "ftag": 0.0,
      "lp": -1
    },
    {
      "home": "Cagliari",
      "away": "Sampdoria",
      "b365h": 2.5,
      "b365a": 2.87,
      "xgh": 1.94,
      "xga": 1.0,
      "dxg": "LH",
      "odd_home_calc": 1.73,
      "odd_away_calc": 5.29,
      "entrada": "HOME",
      "fthg": 0.0,
      "ftag": 0.0,
      "lp": -1
    },
    {
      "home": "Genoa",
      "away": "Chievo",
      "b365h": 1.8,
      "b365a": 5.0,
      "xgh": 0.59,
      "xga": 0.97,
      "dxg": "LA",
      "odd_home_calc": 4.63,
      "odd_away_calc": 2.3,
      "entrada": "AWAY",
      "fthg": 2.0,
      "ftag": 0.0,
      "lp": -1
    },
    {
      "home": "Udinese",
      "away": "Lazio",
      "b365h": 4.2,
      "b365a": 1.85,
      "xgh": 0.45,
      "xga": 2.38,
      "dxg": "FA",
      "odd_home_calc": 18.92,
      "odd_away_calc": 1.3,
      "entrada": "AWAY",
      "fthg": 1.0,
      "ftag": 2.0,
      "lp": 0.85
    },
    {
      "home": "Spal",
      "away": "Sassuolo",
      "b365h": 2.54,
      "b365a": 2.9,
      "xgh": 0.78,
      "xga": 1.06,
      "dxg": "EQ",
      "odd_home_calc": 3.81,
      "odd_away_calc": 2.4,
      "entrada": "AWAY",
      "fthg": 0.0,
      "ftag": 2.0,
      "lp": 1.9
    },
    {
      "home": "Juventus",
      "away": "Napoli",
      "b365h": 1.8,
      "b365a": 4.75,
      "xgh": 1.65,
      "xga": 0.31,
      "dxg": "FH",
      "odd_home_calc": 1.42,
      "odd_away_calc": 15.45,
      "entrada": "HOME",
      "fthg": 3.0,
      "ftag": 1.0,
      "lp": 0.8
    },
    {
      "home": "Roma",
      "away": "Lazio",
      "b365h": 2.37,
      "b365a": 2.9,
      "xgh": 1.53,
      "xga": 0.67,
      "dxg": "LH",
      "odd_home_calc": 1.73,
      "odd_away_calc": 6.19,
      "entrada": "HOME",
      "fthg": 3.0,
      "ftag": 1.0,
      "lp": 1.37
    },
    {
      "home": "Bologna",
      "away": "Udinese",
      "b365h": 2.5,
      "b365a": 3.1,
      "xgh": 1.63,
      "xga": 0.88,
      "dxg": "LH",
      "odd_home_calc": 1.84,
      "odd_away_calc": 4.94,
      "entrada": "HOME",
      "fthg": 2.0,
      "ftag": 1.0,
      "lp": 1.5
    },
    {
      "home": "Chievo",
      "away": "Torino",
      "b365h": 3.75,
      "b365a": 2.1,
      "xgh": 0.48,
      "xga": 2.02,
      "dxg": "FA",
      "odd_home_calc": 12.83,
      "odd_away_calc": 1.39,
      "entrada": "AWAY",
      "fthg": 0.0,
      "ftag": 1.0,
      "lp": 1.1
    },
    {
      "home": "Fiorentina",
      "away": "Atalanta",
      "b365h": 2.25,
      "b365a": 3.25,
      "xgh": 0.66,
      "xga": 0.84,
      "dxg": "EQ",
      "odd_home_calc": 3.78,
      "odd_away_calc": 2.71,
      "entrada": "AWAY",
      "fthg": 2.0,
      "ftag": 0.0,
      "lp": -1
    },
    {
      "home": "Parma",
      "away": "Empoli",
      "b365h": 2.3,
      "b365a": 3.3,
      "xgh": 0.89,
      "xga": 0.88,
      "dxg": "EQ",
      "odd_home_calc": 2.99,
      "odd_away_calc": 3.0,
      "entrada": "HOME",
      "fthg": 1.0,
      "ftag": 0.0,
      "lp": 1.3
    },
    {
      "home": "Sampdoria",
      "away": "Spal",
      "b365h": 1.8,
      "b365a": 4.33,
      "xgh": 1.56,
      "xga": 0.12,
      "dxg": "FH",
      "odd_home_calc": 1.34,
      "odd_away_calc": 20,
      "entrada": "HOME",
      "fthg": 2.0,
      "ftag": 1.0,
      "lp": 0.8
    },
    {
      "home": "Cagliari",
      "away": "Inter",
      "b365h": 5.25,
      "b365a": 1.7,
      "xgh": 1.0,
      "xga": 0.55,
      "dxg": "LH",
      "odd_home_calc": 2.21,
      "odd_away_calc": 5.01,
      "entrada": "HOME",
      "fthg": 2.0,
      "ftag": 1.0,
      "lp": 4.25
    },
    {
      "home": "Cagliari",
      "away": "Bologna",
      "b365h": 2.04,
      "b365a": 3.8,
      "xgh": 1.24,
      "xga": 0.43,
      "dxg": "LH",
      "odd_home_calc": 1.76,
      "odd_away_calc": 7.77,
      "entrada": "HOME",
      "fthg": 2.0,
      "ftag": 0.0,
      "lp": 1.04
    },
    {
      "home": "Empoli",
      "away": "Roma",
      "b365h": 5.5,
      "b365a": 1.61,
      "xgh": 0.65,
      "xga": 0.79,
      "dxg": "EQ",
      "odd_home_calc": 3.71,
      "odd_away_calc": 2.83,
      "entrada": "HOME",
      "fthg": 0.0,
      "ftag": 2.0,
      "lp": -1
    },
    {
      "home": "Napoli",
      "away": "Sassuolo",
      "b365h": 1.33,
      "b365a": 9.0,
      "xgh": 2.25,
      "xga": 1.41,
      "dxg": "LH",
      "odd_home_calc": 1.86,
      "odd_away_calc": 4.33,
      "entrada": "AWAY",
      "fthg": 2.0,
      "ftag": 0.0,
      "lp": -1
    },
    {
      "home": "Genoa",
      "away": "Parma",
      "b365h": 1.75,
      "b365a": 4.75,
      "xgh": 0.78,
      "xga": 0.55,
      "dxg": "EQ",
      "odd_home_calc": 2.66,
      "odd_away_calc": 4.3,
      "entrada": "AWAY",
      "fthg": 1.0,
      "ftag": 3.0,
      "lp": 3.75
    },
    {
      "home": "Udinese",
      "away": "Napoli",
      "b365h": 6.0,
      "b365a": 1.6,
      "xgh": 0.08,
      "xga": 2.85,
      "dxg": "FA",
      "odd_home_calc": 20,
      "odd_away_calc": 1.16,
      "entrada": "AWAY",
      "fthg": 0.0,
      "ftag": 3.0,
      "lp": 0.6
    },
    {
      "home": "Inter",
      "away": "Milan",
      "b365h": 2.45,
      "b365a": 3.0,
      "xgh": 1.04,
      "xga": 1.25,
      "dxg": "EQ",
      "odd_home_calc": 3.28,
      "odd_away_calc": 2.44,
      "entrada": "AWAY",
      "fthg": 1.0,
      "ftag": 0.0,
      "lp": -1
    },
    {
      "home": "Bologna",
      "away": "Torino",
      "b365h": 3.4,
      "b365a": 2.2,
      "xgh": 1.09,
      "xga": 1.33,
      "dxg": "EQ",
      "odd_home_calc": 3.28,
      "odd_away_calc": 2.39,
      "entrada": "AWAY",
      "fthg": 2.0,
      "ftag": 2.0,
      "lp": -1
    },
    {
      "home": "Fiorentina",
      "away": "Cagliari",
      "b365h": 1.5,
      "b365a": 6.0,
      "xgh": 1.75,
      "xga": 2.0,
      "dxg": "EQ",
      "odd_home_calc": 2.98,
      "odd_away_calc": 2.35,
      "entrada": "AWAY",
      "fthg": 1.0,
      "ftag": 1.0,
      "lp": -1
    },
    {
      "home": "Frosinone",
      "away": "Empoli",
      "b365h": 2.9,
      "b365a": 2.5,
      "xgh": 1.2,
      "xga": 0.41,
      "dxg": "LH",
      "odd_home_calc": 1.78,
      "odd_away_calc": 7.91,
      "entrada": "HOME",
      "fthg": 3.0,
      "ftag": 3.0,
      "lp": -1
    },
    {
      "home": "Sampdoria",
      "away": "Sassuolo",
      "b365h": 2.2,
      "b365a": 3.4,
      "xgh": 0.94,
      "xga": 0.71,
      "dxg": "EQ",
      "odd_home_calc": 2.53,
      "odd_away_calc": 3.82,
      "entrada": "HOME",
      "fthg": 0.0,
      "ftag": 0.0,
      "lp": -1
    },
    {
      "home": "Torino",
      "away": "Fiorentina",
      "b365h": 2.4,
      "b365a": 3.1,
      "xgh": 1.36,
      "xga": 0.86,
      "dxg": "LH",
      "odd_home_calc": 2.08,
      "odd_away_calc": 4.21,
      "entrada": "HOME",
      "fthg": 1.0,
      "ftag": 1.0,
      "lp": -1
    },
    {
      "home": "Milan",
      "away": "Sampdoria",
      "b365h": 1.5,
      "b365a": 6.5,
      "xgh": 1.77,
      "xga": 0.98,
      "dxg": "LH",
      "odd_home_calc": 1.82,
      "odd_away_calc": 4.82,
      "entrada": "AWAY",
      "fthg": 3.0,
      "ftag": 2.0,
      "lp": -1
    },
    {
      "home": "Napoli",
      "away": "Roma",
      "b365h": 1.72,
      "b365a": 4.75,
      "xgh": 2.64,
      "xga": 0.45,
      "dxg": "FH",
      "odd_home_calc": 1.27,
      "odd_away_calc": 20,
      "entrada": "HOME",
      "fthg": 1.0,
      "ftag": 1.0,
      "lp": -1
    },
    {
      "home": "Lazio",
      "away": "Inter",
      "b365h": 2.4,
      "b365a": 3.0,
      "xgh": 1.51,
      "xga": 0.81,
      "dxg": "LH",
      "odd_home_calc": 1.88,
      "odd_away_calc": 4.94,
      "entrada": "HOME",
      "fthg": 0.0,
      "ftag": 3.0,
      "lp": -1
    },
    {
      "home": "Juventus",
      "away": "Empoli",
      "b365h": 1.25,
      "b365a": 12.0,
      "xgh": 1.67,
      "xga": 1.0,
      "dxg": "LH",
      "odd_home_calc": 1.91,
      "odd_away_calc": 4.44,
      "entrada": "AWAY",
      "fthg": 1.0,
      "ftag": 0.0,
      "lp": -1
    },
    {
      "home": "Fiorentina",
      "away": "Roma",
      "b365h": 2.7,
      "b365a": 2.6,
      "xgh": 2.68,
      "xga": 1.05,
      "dxg": "FH",
      "odd_home_calc": 1.51,
      "odd_away_calc": 8.09,
      "entrada": "HOME",
      "fthg": 1.0,
      "ftag": 1.0,
      "lp": -1
    },
    {
      "home": "Bologna",
      "away": "Atalanta",
      "b365h": 5.0,
      "b365a": 1.72,
      "xgh": 0.75,
      "xga": 3.03,
      "dxg": "FA",
      "odd_home_calc": 16.1,
      "odd_away_calc": 1.36,
      "entrada": "AWAY",
      "fthg": 1.0,
      "ftag": 2.0,
      "lp": 0.72
    },
    {
      "home": "Chievo",
      "away": "Sassuolo",
      "b365h": 3.6,
      "b365a": 2.1,
      "xgh": 0.64,
      "xga": 0.24,
      "dxg": "LH",
      "odd_home_calc": 2.51,
      "odd_away_calc": 8.31,
      "entrada": "HOME",
      "fthg": 0.0,
      "ftag": 2.0,
      "lp": -1
    },
    {
      "home": "Lazio",
      "away": "Spal",
      "b365h": 1.33,
      "b365a": 10.0,
      "xgh": 1.03,
      "xga": 1.01,
      "dxg": "EQ",
      "odd_home_calc": 2.85,
      "odd_away_calc": 2.92,
      "entrada": "AWAY",
      "fthg": 4.0,
      "ftag": 1.0,
      "lp": -1
    },
    {
      "home": "Parma",
      "away": "Frosinone",
      "b365h": 1.95,
      "b365a": 4.0,
      "xgh": 1.36,
      "xga": 0.46,
      "dxg": "LH",
      "odd_home_calc": 1.69,
      "odd_away_calc": 7.96,
      "entrada": "HOME",
      "fthg": 0.0,
      "ftag": 0.0,
      "lp": -1
    },
    {
      "home": "Udinese",
      "away": "Milan",
      "b365h": 4.2,
      "b365a": 1.9,
      "xgh": 0.45,
      "xga": 1.83,
      "dxg": "FA",
      "odd_home_calc": 11.9,
      "odd_away_calc": 1.43,
      "entrada": "AWAY",
      "fthg": 0.0,
      "ftag": 1.0,
      "lp": 0.9
    },
    {
      "home": "Frosinone",
      "away": "Fiorentina",
      "b365h": 5.25,
      "b365a": 1.7,
      "xgh": 0.92,
      "xga": 0.97,
      "dxg": "EQ",
      "odd_home_calc": 3.05,
      "odd_away_calc": 2.84,
      "entrada": "HOME",
      "fthg": 1.0,
      "ftag": 1.0,
      "lp": -1
    },
    {
      "home": "Genoa",
      "away": "Napoli",
      "b365h": 7.0,
      "b365a": 1.44,
      "xgh": 1.94,
      "xga": 2.27,
      "dxg": "LA",
      "odd_home_calc": 3.08,
      "odd_away_calc": 2.31,
      "entrada": "HOME",
      "fthg": 1.0,
      "ftag": 2.0,
      "lp": -1
    },
    {
      "home": "Spal",
      "away": "Cagliari",
      "b365h": 2.45,
      "b365a": 3.1,
      "xgh": 0.84,
      "xga": 0.74,
      "dxg": "EQ",
      "odd_home_calc": 2.85,
      "odd_away_calc": 3.41,
      "entrada": "HOME",
      "fthg": 2.0,
      "ftag": 2.0,
      "lp": -1
    },
    {
      "home": "Atalanta",
      "away": "Inter",
      "b365h": 2.75,
      "b365a": 2.6,
      "xgh": 0.88,
      "xga": 1.02,
      "dxg": "EQ",
      "odd_home_calc": 3.29,
      "odd_away_calc": 2.64,
      "entrada": "AWAY",
      "fthg": 4.0,
      "ftag": 1.0,
      "lp": -1
    },
    {
      "home": "Chievo",
      "away": "Bologna",
      "b365h": 2.9,
      "b365a": 2.6,
      "xgh": 0.74,
      "xga": 1.47,
      "dxg": "LA",
      "odd_home_calc": 5.3,
      "odd_away_calc": 1.85,
      "entrada": "AWAY",
      "fthg": 2.0,
      "ftag": 2.0,
      "lp": -1
    },
    {
      "home": "Empoli",
      "away": "Udinese",
      "b365h": 2.2,
      "b365a": 3.5,
      "xgh": 0.69,
      "xga": 0.78,
      "dxg": "EQ",
      "odd_home_calc": 3.49,
      "odd_away_calc": 2.94,
      "entrada": "AWAY",
      "fthg": 2.0,
      "ftag": 1.0,
      "lp": -1
    },
    {
      "home": "Roma",
      "away": "Sampdoria",
      "b365h": 1.44,
      "b365a": 7.0,
      "xgh": 1.79,
      "xga": 1.17,
      "dxg": "LH",
      "odd_home_calc": 1.97,
      "odd_away_calc": 4.01,
      "entrada": "AWAY",
      "fthg": 4.0,
      "ftag": 1.0,
      "lp": -1
    },
    {
      "home": "Sassuolo",
      "away": "Lazio",
      "b365h": 4.0,
      "b365a": 1.95,
      "xgh": 0.28,
      "xga": 2.38,
      "dxg": "FA",
      "odd_home_calc": 20,
      "odd_away_calc": 1.24,
      "entrada": "AWAY",
      "fthg": 1.0,
      "ftag": 1.0,
      "lp": -1
    },
    {
      "home": "Udinese",
      "away": "Roma",
      "b365h": 4.5,
      "b365a": 1.83,
      "xgh": 0.44,
      "xga": 1.53,
      "dxg": "FA",
      "odd_home_calc": 9.73,
      "odd_away_calc": 1.56,
      "entrada": "AWAY",
      "fthg": 1.0,
      "ftag": 0.0,
      "lp": -1
    },
    {
      "home": "Bologna",
      "away": "Fiorentina",
      "b365h": 4.0,
      "b365a": 2.04,
      "xgh": 0.95,
      "xga": 2.17,
      "dxg": "FA",
      "odd_home_calc": 6.54,
      "odd_away_calc": 1.59,
      "entrada": "AWAY",
      "fthg": 0.0,
      "ftag": 0.0,
      "lp": -1
    },
    {
      "home": "Empoli",
      "away": "Atalanta",
      "b365h": 5.25,
      "b365a": 1.66,
      "xgh": 0.59,
      "xga": 2.84,
      "dxg": "FA",
      "odd_home_calc": 19.33,
      "odd_away_calc": 1.31,
      "entrada": "AWAY",
      "fthg": 3.0,
      "ftag": 2.0,
      "lp": -1
    },
    {
      "home": "Genoa",
      "away": "Sampdoria",
      "b365h": 2.6,
      "b365a": 2.75,
      "xgh": 1.1,
      "xga": 1.0,
      "dxg": "EQ",
      "odd_home_calc": 2.65,
      "odd_away_calc": 3.1,
      "entrada": "HOME",
      "fthg": 1.0,
      "ftag": 1.0,
      "lp": -1
    },
    {
      "home": "Lazio",
      "away": "Milan",
      "b365h": 1.85,
      "b365a": 4.2,
      "xgh": 1.38,
      "xga": 1.2,
      "dxg": "EQ",
      "odd_home_calc": 2.46,
      "odd_away_calc": 3.07,
      "entrada": "AWAY",
      "fthg": 1.0,
      "ftag": 1.0,
      "lp": -1
    },
    {
      "home": "Cagliari",
      "away": "Torino",
      "b365h": 2.9,
      "b365a": 2.54,
      "xgh": 1.21,
      "xga": 1.23,
      "dxg": "EQ",
      "odd_home_calc": 2.81,
      "odd_away_calc": 2.72,
      "entrada": "AWAY",
      "fthg": 0.0,
      "ftag": 0.0,
      "lp": -1
    },
    {
      "home": "Sampdoria",
      "away": "Bologna",
      "b365h": 2.0,
      "b365a": 4.0,
      "xgh": 1.93,
      "xga": 0.41,
      "dxg": "FH",
      "odd_home_calc": 1.38,
      "odd_away_calc": 14.31,
      "entrada": "HOME",
      "fthg": 4.0,
      "ftag": 1.0,
      "lp": 1.0
    },
    {
      "home": "Spal",
      "away": "Empoli",
      "b365h": 2.4,
      "b365a": 3.0,
      "xgh": 0.98,
      "xga": 1.39,
      "dxg": "LA",
      "odd_home_calc": 3.81,
      "odd_away_calc": 2.16,
      "entrada": "AWAY",
      "fthg": 2.0,
      "ftag": 2.0,
      "lp": -1
    },
    {
      "home": "Sassuolo",
      "away": "Udinese",
      "b365h": 1.9,
      "b365a": 4.0,
      "xgh": 0.88,
      "xga": 0.84,
      "dxg": "EQ",
      "odd_home_calc": 2.92,
      "odd_away_calc": 3.13,
      "entrada": "AWAY",
      "fthg": 0.0,
      "ftag": 0.0,
      "lp": -1
    },
    {
      "home": "Torino",
      "away": "Genoa",
      "b365h": 1.75,
      "b365a": 4.75,
      "xgh": 1.66,
      "xga": 0.28,
      "dxg": "FH",
      "odd_home_calc": 1.4,
      "odd_away_calc": 17.42,
      "entrada": "HOME",
      "fthg": 2.0,
      "ftag": 1.0,
      "lp": 0.75
    },
    {
      "home": "Milan",
      "away": "Parma",
      "b365h": 1.4,
      "b365a": 7.5,
      "xgh": 1.28,
      "xga": 2.1,
      "dxg": "LA",
      "odd_home_calc": 4.39,
      "odd_away_calc": 1.85,
      "entrada": "AWAY",
      "fthg": 2.0,
      "ftag": 1.0,
      "lp": -1
    },
    {
      "home": "Frosinone",
      "away": "Cagliari",
      "b365h": 3.0,
      "b365a": 2.4,
      "xgh": 1.34,
      "xga": 2.0,
      "dxg": "LA",
      "odd_home_calc": 3.95,
      "odd_away_calc": 1.96,
      "entrada": "AWAY",
      "fthg": 1.0,
      "ftag": 1.0,
      "lp": -1
    },
    {
      "home": "Chievo",
      "away": "Lazio",
      "b365h": 8.0,
      "b365a": 1.44,
      "xgh": 0.48,
      "xga": 1.06,
      "dxg": "LA",
      "odd_home_calc": 6.12,
      "odd_away_calc": 2.01,
      "entrada": "HOME",
      "fthg": 1.0,
      "ftag": 1.0,
      "lp": -1
    },
    {
      "home": "Atalanta",
      "away": "Napoli",
      "b365h": 3.3,
      "b365a": 2.14,
      "xgh": 0.76,
      "xga": 1.59,
      "dxg": "LA",
      "odd_home_calc": 5.6,
      "odd_away_calc": 1.77,
      "entrada": "AWAY",
      "fthg": 1.0,
      "ftag": 2.0,
      "lp": 1.14
    },
    {
      "home": "Lazio",
      "away": "Sampdoria",
      "b365h": 1.44,
      "b365a": 7.0,
      "xgh": 1.42,
      "xga": 1.15,
      "dxg": "EQ",
      "odd_home_calc": 2.33,
      "odd_away_calc": 3.29,
      "entrada": "AWAY",
      "fthg": 2.0,
      "ftag": 2.0,
      "lp": -1
    },
    {
      "home": "Napoli",
      "away": "Frosinone",
      "b365h": 1.16,
      "b365a": 15.0,
      "xgh": 3.18,
      "xga": 1.44,
      "dxg": "FH",
      "odd_home_calc": 1.63,
      "odd_away_calc": 7.32,
      "entrada": "AWAY",
      "fthg": 4.0,
      "ftag": 0.0,
      "lp": -1
    },
    {
      "home": "Sassuolo",
      "away": "Fiorentina",
      "b365h": 2.8,
      "b365a": 2.6,
      "xgh": 0.49,
      "xga": 0.75,
      "dxg": "EQ",
      "odd_home_calc": 4.63,
      "odd_away_calc": 2.65,
      "entrada": "AWAY",
      "fthg": 3.0,
      "ftag": 3.0,
      "lp": -1
    },
    {
      "home": "Empoli",
      "away": "Bologna",
      "b365h": 1.95,
      "b365a": 4.0,
      "xgh": 1.31,
      "xga": 0.33,
      "dxg": "LH",
      "odd_home_calc": 1.62,
      "odd_away_calc": 10.68,
      "entrada": "HOME",
      "fthg": 2.0,
      "ftag": 1.0,
      "lp": 0.95
    },
    {
      "home": "Milan",
      "away": "Torino",
      "b365h": 1.85,
      "b365a": 4.33,
      "xgh": 2.33,
      "xga": 1.19,
      "dxg": "FH",
      "odd_home_calc": 1.68,
      "odd_away_calc": 5.53,
      "entrada": "HOME",
      "fthg": 0.0,
      "ftag": 0.0,
      "lp": -1
    },
    {
      "home": "Inter",
      "away": "Udinese",
      "b365h": 1.3,
      "b365a": 11.0,
      "xgh": 1.81,
      "xga": 1.0,
      "dxg": "LH",
      "odd_home_calc": 1.81,
      "odd_away_calc": 4.83,
      "entrada": "AWAY",
      "fthg": 1.0,
      "ftag": 0.0,
      "lp": -1
    },
    {
      "home": "Sampdoria",
      "away": "Parma",
      "b365h": 1.83,
      "b365a": 4.5,
      "xgh": 1.56,
      "xga": 1.52,
      "dxg": "EQ",
      "odd_home_calc": 2.61,
      "odd_away_calc": 2.72,
      "entrada": "AWAY",
      "fthg": 2.0,
      "ftag": 0.0,
      "lp": -1
    },
    {
      "home": "Cagliari",
      "away": "Napoli",
      "b365h": 7.5,
      "b365a": 1.44,
      "xgh": 1.05,
      "xga": 2.25,
      "dxg": "FA",
      "odd_home_calc": 6.14,
      "odd_away_calc": 1.62,
      "entrada": "HOME",
      "fthg": 0.0,
      "ftag": 1.0,
      "lp": -1
    },
    {
      "home": "Fiorentina",
      "away": "Empoli",
      "b365h": 1.75,
      "b365a": 4.75,
      "xgh": 1.32,
      "xga": 0.16,
      "dxg": "FH",
      "odd_home_calc": 1.48,
      "odd_away_calc": 20,
      "entrada": "HOME",
      "fthg": 3.0,
      "ftag": 1.0,
      "lp": 0.75
    },
    {
      "home": "Frosinone",
      "away": "Sassuolo",
      "b365h": 3.6,
      "b365a": 2.04,
      "xgh": 0.14,
      "xga": 1.38,
      "dxg": "FA",
      "odd_home_calc": 20,
      "odd_away_calc": 1.43,
      "entrada": "AWAY",
      "fthg": 0.0,
      "ftag": 2.0,
      "lp": 1.04
    },
    {
      "home": "Atalanta",
      "away": "Lazio",
      "b365h": 2.2,
      "b365a": 3.1,
      "xgh": 2.11,
      "xga": 0.37,
      "dxg": "FH",
      "odd_home_calc": 1.31,
      "odd_away_calc": 18.87,
      "entrada": "HOME",
      "fthg": 1.0,
      "ftag": 0.0,
      "lp": 1.2
    },
    {
      "home": "Bologna",
      "away": "Milan",
      "b365h": 4.2,
      "b365a": 1.95,
      "xgh": 0.33,
      "xga": 1.69,
      "dxg": "FA",
      "odd_home_calc": 14.96,
      "odd_away_calc": 1.41,
      "entrada": "AWAY",
      "fthg": 0.0,
      "ftag": 0.0,
      "lp": -1
    },
    {
      "home": "Sassuolo",
      "away": "Torino",
      "b365h": 2.62,
      "b365a": 2.8,
      "xgh": 0.6,
      "xga": 1.36,
      "dxg": "LA",
      "odd_home_calc": 6.09,
      "odd_away_calc": 1.81,
      "entrada": "AWAY",
      "fthg": 1.0,
      "ftag": 1.0,
      "lp": -1
    },
    {
      "home": "Parma",
      "away": "Bologna",
      "b365h": 2.54,
      "b365a": 3.0,
      "xgh": 0.97,
      "xga": 0.71,
      "dxg": "EQ",
      "odd_home_calc": 2.47,
      "odd_away_calc": 3.91,
      "entrada": "HOME",
      "fthg": 0.0,
      "ftag": 0.0,
      "lp": -1
    },
    {
      "home": "Milan",
      "away": "Fiorentina",
      "b365h": 2.3,
      "b365a": 3.25,
      "xgh": 2.19,
      "xga": 0.75,
      "dxg": "FH",
      "odd_home_calc": 1.47,
      "odd_away_calc": 8.85,
      "entrada": "HOME",
      "fthg": 0.0,
      "ftag": 1.0,
      "lp": -1
    },
    {
      "home": "Udinese",
      "away": "Frosinone",
      "b365h": 1.7,
      "b365a": 5.25,
      "xgh": 1.67,
      "xga": 0.24,
      "dxg": "FH",
      "odd_home_calc": 1.37,
      "odd_away_calc": 20,
      "entrada": "HOME",
      "fthg": 1.0,
      "ftag": 1.0,
      "lp": -1
    },
    {
      "home": "Genoa",
      "away": "Atalanta",
      "b365h": 4.0,
      "b365a": 1.9,
      "xgh": 0.98,
      "xga": 0.59,
      "dxg": "LH",
      "odd_home_calc": 2.28,
      "odd_away_calc": 4.69,
      "entrada": "HOME",
      "fthg": 3.0,
      "ftag": 1.0,
      "lp": 3.0
    },
    {
      "home": "Empoli",
      "away": "Sampdoria",
      "b365h": 2.3,
      "b365a": 3.1,
      "xgh": 0.57,
      "xga": 0.64,
      "dxg": "EQ",
      "odd_home_calc": 3.71,
      "odd_away_calc": 3.21,
      "entrada": "HOME",
      "fthg": 2.0,
      "ftag": 4.0,
      "lp": -1
    },
    {
      "home": "Lazio",
      "away": "Cagliari",
      "b365h": 1.33,
      "b365a": 9.0,
      "xgh": 2.29,
      "xga": 1.0,
      "dxg": "FH",
      "odd_home_calc": 1.58,
      "odd_away_calc": 6.66,
      "entrada": "AWAY",
      "fthg": 3.0,
      "ftag": 1.0,
      "lp": -1
    },
    {
      "home": "Torino",
      "away": "Empoli",
      "b365h": 1.7,
      "b365a": 5.0,
      "xgh": 1.86,
      "xga": 0.27,
      "dxg": "FH",
      "odd_home_calc": 1.32,
      "odd_away_calc": 20,
      "entrada": "HOME",
      "fthg": 3.0,
      "ftag": 0.0,
      "lp": 0.7
    },
    {
      "home": "Atalanta",
      "away": "Juventus",
      "b365h": 4.75,
      "b365a": 1.8,
      "xgh": 1.61,
      "xga": 1.48,
      "dxg": "EQ",
      "odd_home_calc": 2.48,
      "odd_away_calc": 2.87,
      "entrada": "HOME",
      "fthg": 2.0,
      "ftag": 2.0,
      "lp": -1
    },
    {
      "home": "Bologna",
      "away": "Lazio",
      "b365h": 5.0,
      "b365a": 1.72,
      "xgh": 0.77,
      "xga": 1.09,
      "dxg": "LA",
      "odd_home_calc": 3.91,
      "odd_away_calc": 2.34,
      "entrada": "HOME",
      "fthg": 0.0,
      "ftag": 2.0,
      "lp": -1
    },
    {
      "home": "Cagliari",
      "away": "Genoa",
      "b365h": 2.3,
      "b365a": 3.3,
      "xgh": 1.68,
      "xga": 0.9,
      "dxg": "LH",
      "odd_home_calc": 1.81,
      "odd_away_calc": 5.02,
      "entrada": "HOME",
      "fthg": 1.0,
      "ftag": 0.0,
      "lp": 1.3
    },
    {
      "home": "Frosinone",
      "away": "Milan",
      "b365h": 5.25,
      "b365a": 1.7,
      "xgh": 0.91,
      "xga": 1.33,
      "dxg": "LA",
      "odd_home_calc": 3.91,
      "odd_away_calc": 2.17,
      "entrada": "HOME",
      "fthg": 0.0,
      "ftag": 0.0,
      "lp": -1
    },
    {
      "home": "Inter",
      "away": "Napoli",
      "b365h": 2.75,
      "b365a": 2.62,
      "xgh": 0.4,
      "xga": 1.14,
      "dxg": "LA",
      "odd_home_calc": 7.77,
      "odd_away_calc": 1.83,
      "entrada": "AWAY",
      "fthg": 1.0,
      "ftag": 0.0,
      "lp": -1
    },
    {
      "home": "Roma",
      "away": "Sassuolo",
      "b365h": 1.61,
      "b365a": 5.25,
      "xgh": 1.62,
      "xga": 1.98,
      "dxg": "LA",
      "odd_home_calc": 3.19,
      "odd_away_calc": 2.23,
      "entrada": "AWAY",
      "fthg": 3.0,
      "ftag": 1.0,
      "lp": -1
    },
    {
      "home": "Sampdoria",
      "away": "Chievo",
      "b365h": 1.75,
      "b365a": 5.0,
      "xgh": 2.25,
      "xga": 0.41,
      "dxg": "FH",
      "odd_home_calc": 1.3,
      "odd_away_calc": 18.98,
      "entrada": "HOME",
      "fthg": 2.0,
      "ftag": 0.0,
      "lp": 0.75
    },
    {
      "home": "Spal",
      "away": "Udinese",
      "b365h": 2.5,
      "b365a": 3.1,
      "xgh": 1.09,
      "xga": 0.88,
      "dxg": "EQ",
      "odd_home_calc": 2.51,
      "odd_away_calc": 3.43,
      "entrada": "HOME",
      "fthg": 0.0,
      "ftag": 0.0,
      "lp": -1
    },
    {
      "home": "Napoli",
      "away": "Bologna",
      "b365h": 1.28,
      "b365a": 10.0,
      "xgh": 2.51,
      "xga": 0.97,
      "dxg": "FH",
      "odd_home_calc": 1.5,
      "odd_away_calc": 7.98,
      "entrada": "AWAY",
      "fthg": 3.0,
      "ftag": 2.0,
      "lp": -1
    },
    {
      "home": "Sassuolo",
      "away": "Atalanta",
      "b365h": 3.4,
      "b365a": 2.04,
      "xgh": 0.15,
      "xga": 0.25,
      "dxg": "EQ",
      "odd_home_calc": 9.18,
      "odd_away_calc": 5.24,
      "entrada": "AWAY",
      "fthg": 2.0,
      "ftag": 6.0,
      "lp": 1.04
    },
    {
      "home": "Juventus",
      "away": "Sampdoria",
      "b365h": 1.2,
      "b365a": 13.0,
      "xgh": 2.16,
      "xga": 2.98,
      "dxg": "LA",
      "odd_home_calc": 3.91,
      "odd_away_calc": 2.12,
      "entrada": "AWAY",
      "fthg": 2.0,
      "ftag": 1.0,
      "lp": -1
    },
    {
      "home": "Genoa",
      "away": "Fiorentina",
      "b365h": 2.54,
      "b365a": 2.7,
      "xgh": 0.54,
      "xga": 2.45,
      "dxg": "FA",
      "odd_home_calc": 16.02,
      "odd_away_calc": 1.32,
      "entrada": "AWAY",
      "fthg": 0.0,
      "ftag": 0.0,
      "lp": -1
    },
    {
      "home": "Inter",
      "away": "Sassuolo",
      "b365h": 1.4,
      "b365a": 8.0,
      "xgh": 1.57,
      "xga": 0.82,
      "dxg": "LH",
      "odd_home_calc": 1.84,
      "odd_away_calc": 5.12,
      "entrada": "AWAY",
      "fthg": 0.0,
      "ftag": 0.0,
      "lp": -1
    },
    {
      "home": "Udinese",
      "away": "Parma",
      "b365h": 2.1,
      "b365a": 4.0,
      "xgh": 0.85,
      "xga": 0.12,
      "dxg": "LH",
      "odd_home_calc": 1.89,
      "odd_away_calc": 18.91,
      "entrada": "HOME",
      "fthg": 1.0,
      "ftag": 2.0,
      "lp": -1
    },
    {
      "home": "Napoli",
      "away": "Lazio",
      "b365h": 1.9,
      "b365a": 4.0,
      "xgh": 3.26,
      "xga": 0.7,
      "dxg": "FH",
      "odd_home_calc": 1.34,
      "odd_away_calc": 20,
      "entrada": "HOME",
      "fthg": 2.0,
      "ftag": 1.0,
      "lp": 0.9
    },
    {
      "home": "Cagliari",
      "away": "Empoli",
      "b365h": 2.0,
      "b365a": 3.8,
      "xgh": 1.3,
      "xga": 0.22,
      "dxg": "FH",
      "odd_home_calc": 1.54,
      "odd_away_calc": 16.26,
      "entrada": "HOME",
      "fthg": 2.0,
      "ftag": 2.0,
      "lp": -1
    },
    {
      "home": "Milan",
      "away": "Napoli",
      "b365h": 3.75,
      "b365a": 2.0,
      "xgh": 0.55,
      "xga": 1.72,
      "dxg": "FA",
      "odd_home_calc": 8.85,
      "odd_away_calc": 1.53,
      "entrada": "AWAY",
      "fthg": 0.0,
      "ftag": 0.0,
      "lp": -1
    },
    {
      "home": "Torino",
      "away": "Inter",
      "b365h": 3.6,
      "b365a": 2.1,
      "xgh": 1.07,
      "xga": 1.19,
      "dxg": "EQ",
      "odd_home_calc": 3.07,
      "odd_away_calc": 2.59,
      "entrada": "HOME",
      "fthg": 1.0,
      "ftag": 0.0,
      "lp": 2.6
    },
    {
      "home": "Lazio",
      "away": "Juventus",
      "b365h": 4.2,
      "b365a": 1.9,
      "xgh": 0.12,
      "xga": 1.86,
      "dxg": "FA",
      "odd_home_calc": 20,
      "odd_away_calc": 1.25,
      "entrada": "AWAY",
      "fthg": 1.0,
      "ftag": 2.0,
      "lp": 0.9
    },
    {
      "home": "Parma",
      "away": "Spal",
      "b365h": 2.4,
      "b365a": 3.3,
      "xgh": 0.92,
      "xga": 1.62,
      "dxg": "LA",
      "odd_home_calc": 4.69,
      "odd_away_calc": 1.88,
      "entrada": "AWAY",
      "fthg": 2.0,
      "ftag": 3.0,
      "lp": 2.3
    },
    {
      "home": "Bologna",
      "away": "Frosinone",
      "b365h": 1.65,
      "b365a": 5.5,
      "xgh": 2.53,
      "xga": 0.24,
      "dxg": "FH",
      "odd_home_calc": 1.21,
      "odd_away_calc": 20,
      "entrada": "HOME",
      "fthg": 0.0,
      "ftag": 4.0,
      "lp": -1
    },
    {
      "home": "Atalanta",
      "away": "Roma",
      "b365h": 2.15,
      "b365a": 3.25,
      "xgh": 1.7,
      "xga": 0.98,
      "dxg": "LH",
      "odd_home_calc": 1.87,
      "odd_away_calc": 4.63,
      "entrada": "HOME",
      "fthg": 3.0,
      "ftag": 3.0,
      "lp": -1
    },
    {
      "home": "Chievo",
      "away": "Fiorentina",
      "b365h": 4.5,
      "b365a": 1.83,
      "xgh": 0.11,
      "xga": 1.52,
      "dxg": "FA",
      "odd_home_calc": 20,
      "odd_away_calc": 1.35,
      "entrada": "AWAY",
      "fthg": 3.0,
      "ftag": 4.0,
      "lp": 0.83
    },
    {
      "home": "Empoli",
      "away": "Genoa",
      "b365h": 2.37,
      "b365a": 3.0,
      "xgh": 0.85,
      "xga": 1.26,
      "dxg": "LA",
      "odd_home_calc": 4.0,
      "odd_away_calc": 2.19,
      "entrada": "AWAY",
      "fthg": 1.0,
      "ftag": 3.0,
      "lp": 2.0
    },
    {
      "home": "Empoli",
      "away": "Chievo",
      "b365h": 1.95,
      "b365a": 4.0,
      "xgh": 1.37,
      "xga": 0.4,
      "dxg": "LH",
      "odd_home_calc": 1.63,
      "odd_away_calc": 9.39,
      "entrada": "HOME",
      "fthg": 2.0,
      "ftag": 2.0,
      "lp": -1
    },
    {
      "home": "Genoa",
      "away": "Sassuolo",
      "b365h": 2.5,
      "b365a": 2.87,
      "xgh": 1.01,
      "xga": 1.3,
      "dxg": "EQ",
      "odd_home_calc": 3.48,
      "odd_away_calc": 2.32,
      "entrada": "AWAY",
      "fthg": 1.0,
      "ftag": 1.0,
      "lp": -1
    },
    {
      "home": "Inter",
      "away": "Bologna",
      "b365h": 1.33,
      "b365a": 9.0,
      "xgh": 1.41,
      "xga": 0.59,
      "dxg": "LH",
      "odd_home_calc": 1.76,
      "odd_away_calc": 6.41,
      "entrada": "AWAY",
      "fthg": 0.0,
      "ftag": 1.0,
      "lp": 8.0
    },
    {
      "home": "Roma",
      "away": "Milan",
      "b365h": 2.15,
      "b365a": 3.4,
      "xgh": 1.58,
      "xga": 0.77,
      "dxg": "LH",
      "odd_home_calc": 1.78,
      "odd_away_calc": 5.53,
      "entrada": "HOME",
      "fthg": 1.0,
      "ftag": 1.0,
      "lp": -1
    },
    {
      "home": "Spal",
      "away": "Torino",
      "b365h": 3.7,
      "b365a": 2.15,
      "xgh": 2.0,
      "xga": 1.43,
      "dxg": "LH",
      "odd_home_calc": 2.04,
      "odd_away_calc": 3.66,
      "entrada": "HOME",
      "fthg": 0.0,
      "ftag": 0.0,
      "lp": -1
    },
    {
      "home": "Udinese",
      "away": "Fiorentina",
      "b365h": 3.6,
      "b365a": 2.1,
      "xgh": 0.6,
      "xga": 2.21,
      "dxg": "FA",
      "odd_home_calc": 11.6,
      "odd_away_calc": 1.39,
      "entrada": "AWAY",
      "fthg": 1.0,
      "ftag": 1.0,
      "lp": -1
    },
    {
      "home": "Parma",
      "away": "Inter",
      "b365h": 5.25,
      "b365a": 1.66,
      "xgh": 0.4,
      "xga": 0.63,
      "dxg": "EQ",
      "odd_home_calc": 5.09,
      "odd_away_calc": 2.85,
      "entrada": "AWAY",
      "fthg": 0.0,
      "ftag": 1.0,
      "lp": 0.66
    },
    {
      "home": "Milan",
      "away": "Cagliari",
      "b365h": 1.4,
      "b365a": 8.5,
      "xgh": 1.24,
      "xga": 0.9,
      "dxg": "LH",
      "odd_home_calc": 2.28,
      "odd_away_calc": 3.74,
      "entrada": "AWAY",
      "fthg": 3.0,
      "ftag": 0.0,
      "lp": -1
    },
    {
      "home": "Sassuolo",
      "away": "Juventus",
      "b365h": 7.0,
      "b365a": 1.57,
      "xgh": 0.07,
      "xga": 1.96,
      "dxg": "FA",
      "odd_home_calc": 20,
      "odd_away_calc": 1.21,
      "entrada": "AWAY",
      "fthg": 0.0,
      "ftag": 3.0,
      "lp": 0.57
    },
    {
      "home": "Cagliari",
      "away": "Parma",
      "b365h": 2.0,
      "b365a": 4.0,
      "xgh": 1.6,
      "xga": 0.4,
      "dxg": "FH",
      "odd_home_calc": 1.5,
      "odd_away_calc": 11.31,
      "entrada": "HOME",
      "fthg": 2.0,
      "ftag": 1.0,
      "lp": 1.0
    },
    {
      "home": "Atalanta",
      "away": "Milan",
      "b365h": 2.0,
      "b365a": 3.9,
      "xgh": 0.88,
      "xga": 1.81,
      "dxg": "LA",
      "odd_home_calc": 5.57,
      "odd_away_calc": 1.72,
      "entrada": "AWAY",
      "fthg": 1.0,
      "ftag": 3.0,
      "lp": 2.9
    },
    {
      "home": "Empoli",
      "away": "Sassuolo",
      "b365h": 2.7,
      "b365a": 2.6,
      "xgh": 1.86,
      "xga": 1.28,
      "dxg": "LH",
      "odd_home_calc": 2.01,
      "odd_away_calc": 3.82,
      "entrada": "HOME",
      "fthg": 3.0,
      "ftag": 0.0,
      "lp": 1.7
    },
    {
      "home": "Genoa",
      "away": "Lazio",
      "b365h": 3.2,
      "b365a": 2.25,
      "xgh": 0.45,
      "xga": 1.24,
      "dxg": "LA",
      "odd_home_calc": 7.37,
      "odd_away_calc": 1.79,
      "entrada": "AWAY",
      "fthg": 2.0,
      "ftag": 1.0,
      "lp": -1
    },
    {
      "home": "Napoli",
      "away": "Torino",
      "b365h": 1.44,
      "b365a": 8.0,
      "xgh": 2.19,
      "xga": 1.14,
      "dxg": "FH",
      "odd_home_calc": 1.71,
      "odd_away_calc": 5.29,
      "entrada": "AWAY",
      "fthg": 0.0,
      "ftag": 0.0,
      "lp": -1
    },
    {
      "home": "Spal",
      "away": "Fiorentina",
      "b365h": 3.6,
      "b365a": 2.15,
      "xgh": 0.76,
      "xga": 1.98,
      "dxg": "FA",
      "odd_home_calc": 7.51,
      "odd_away_calc": 1.55,
      "entrada": "AWAY",
      "fthg": 1.0,
      "ftag": 4.0,
      "lp": 1.15
    },
    {
      "home": "Udinese",
      "away": "Chievo",
      "b365h": 1.83,
      "b365a": 4.75,
      "xgh": 1.97,
      "xga": 0.67,
      "dxg": "FH",
      "odd_home_calc": 1.5,
      "odd_away_calc": 8.52,
      "entrada": "HOME",
      "fthg": 1.0,
      "ftag": 0.0,
      "lp": 0.83
    },
    {
      "home": "Milan",
      "away": "Empoli",
      "b365h": 1.44,
      "b365a": 7.0,
      "xgh": 1.28,
      "xga": 0.65,
      "dxg": "LH",
      "odd_home_calc": 1.95,
      "odd_away_calc": 5.25,
      "entrada": "AWAY",
      "fthg": 3.0,
      "ftag": 0.0,
      "lp": -1
    },
    {
      "home": "Sassuolo",
      "away": "Spal",
      "b365h": 1.95,
      "b365a": 4.0,
      "xgh": 0.94,
      "xga": 0.99,
      "dxg": "EQ",
      "odd_home_calc": 3.04,
      "odd_away_calc": 2.81,
      "entrada": "AWAY",
      "fthg": 1.0,
      "ftag": 1.0,
      "lp": -1
    },
    {
      "home": "Sampdoria",
      "away": "Cagliari",
      "b365h": 1.75,
      "b365a": 5.0,
      "xgh": 2.35,
      "xga": 1.0,
      "dxg": "FH",
      "odd_home_calc": 1.56,
      "odd_away_calc": 6.94,
      "entrada": "HOME",
      "fthg": 1.0,
      "ftag": 0.0,
      "lp": 0.75
    },
    {
      "home": "Bologna",
      "away": "Juventus",
      "b365h": 7.5,
      "b365a": 1.44,
      "xgh": 1.48,
      "xga": 2.17,
      "dxg": "LA",
      "odd_home_calc": 3.88,
      "odd_away_calc": 1.96,
      "entrada": "HOME",
      "fthg": 0.0,
      "ftag": 1.0,
      "lp": -1
    },
    {
      "home": "Chievo",
      "away": "Genoa",
      "b365h": 3.3,
      "b365a": 2.3,
      "xgh": 0.9,
      "xga": 1.58,
      "dxg": "LA",
      "odd_home_calc": 4.65,
      "odd_away_calc": 1.9,
      "entrada": "AWAY",
      "fthg": 0.0,
      "ftag": 0.0,
      "lp": -1
    },
    {
      "home": "Fiorentina",
      "away": "Inter",
      "b365h": 2.7,
      "b365a": 2.7,
      "xgh": 1.76,
      "xga": 1.28,
      "dxg": "LH",
      "odd_home_calc": 2.09,
      "odd_away_calc": 3.61,
      "entrada": "HOME",
      "fthg": 3.0,
      "ftag": 3.0,
      "lp": -1
    },
    {
      "home": "Lazio",
      "away": "Udinese",
      "b365h": 1.36,
      "b365a": 8.5,
      "xgh": 1.94,
      "xga": 0.96,
      "dxg": "LH",
      "odd_home_calc": 1.7,
      "odd_away_calc": 5.54,
      "entrada": "AWAY",
      "fthg": 2.0,
      "ftag": 0.0,
      "lp": -1
    },
    {
      "home": "Lazio",
      "away": "Roma",
      "b365h": 2.37,
      "b365a": 3.0,
      "xgh": 1.33,
      "xga": 1.1,
      "dxg": "EQ",
      "odd_home_calc": 2.4,
      "odd_away_calc": 3.25,
      "entrada": "HOME",
      "fthg": 3.0,
      "ftag": 0.0,
      "lp": 1.37
    },
    {
      "home": "Milan",
      "away": "Sassuolo",
      "b365h": 1.5,
      "b365a": 7.0,
      "xgh": 1.2,
      "xga": 0.87,
      "dxg": "LH",
      "odd_home_calc": 2.31,
      "odd_away_calc": 3.73,
      "entrada": "AWAY",
      "fthg": 1.0,
      "ftag": 0.0,
      "lp": -1
    },
    {
      "home": "Torino",
      "away": "Chievo",
      "b365h": 1.44,
      "b365a": 8.0,
      "xgh": 3.11,
      "xga": 0.42,
      "dxg": "FH",
      "odd_home_calc": 1.26,
      "odd_away_calc": 20,
      "entrada": "HOME",
      "fthg": 3.0,
      "ftag": 0.0,
      "lp": 0.44
    },
    {
      "home": "Juventus",
      "away": "Udinese",
      "b365h": 1.36,
      "b365a": 9.5,
      "xgh": 1.79,
      "xga": 0.81,
      "dxg": "LH",
      "odd_home_calc": 1.68,
      "odd_away_calc": 6.03,
      "entrada": "AWAY",
      "fthg": 4.0,
      "ftag": 1.0,
      "lp": -1
    },
    {
      "home": "Parma",
      "away": "Genoa",
      "b365h": 2.8,
      "b365a": 2.7,
      "xgh": 2.82,
      "xga": 0.35,
      "dxg": "FH",
      "odd_home_calc": 1.23,
      "odd_away_calc": 20,
      "entrada": "HOME",
      "fthg": 1.0,
      "ftag": 0.0,
      "lp": 1.8
    },
    {
      "home": "Sampdoria",
      "away": "Atalanta",
      "b365h": 3.5,
      "b365a": 2.15,
      "xgh": 0.58,
      "xga": 1.58,
      "dxg": "LA",
      "odd_home_calc": 7.45,
      "odd_away_calc": 1.63,
      "entrada": "AWAY",
      "fthg": 1.0,
      "ftag": 2.0,
      "lp": 1.15
    },
    {
      "home": "Inter",
      "away": "Spal",
      "b365h": 1.4,
      "b365a": 8.5,
      "xgh": 1.6,
      "xga": 2.05,
      "dxg": "LA",
      "odd_home_calc": 3.37,
      "odd_away_calc": 2.14,
      "entrada": "AWAY",
      "fthg": 2.0,
      "ftag": 0.0,
      "lp": -1
    },
    {
      "home": "Sassuolo",
      "away": "Napoli",
      "b365h": 6.0,
      "b365a": 1.57,
      "xgh": 0.08,
      "xga": 2.88,
      "dxg": "FA",
      "odd_home_calc": 20,
      "odd_away_calc": 1.17,
      "entrada": "AWAY",
      "fthg": 1.0,
      "ftag": 1.0,
      "lp": -1
    },
    {
      "home": "Fiorentina",
      "away": "Lazio",
      "b365h": 2.8,
      "b365a": 2.55,
      "xgh": 1.92,
      "xga": 1.11,
      "dxg": "LH",
      "odd_home_calc": 1.83,
      "odd_away_calc": 4.62,
      "entrada": "HOME",
      "fthg": 1.0,
      "ftag": 1.0,
      "lp": -1
    },
    {
      "home": "Frosinone",
      "away": "Torino",
      "b365h": 4.75,
      "b365a": 1.85,
      "xgh": 1.0,
      "xga": 2.25,
      "dxg": "FA",
      "odd_home_calc": 6.46,
      "odd_away_calc": 1.59,
      "entrada": "AWAY",
      "fthg": 1.0,
      "ftag": 2.0,
      "lp": 0.85
    },
    {
      "home": "Roma",
      "away": "Empoli",
      "b365h": 1.53,
      "b365a": 5.75,
      "xgh": 2.0,
      "xga": 3.07,
      "dxg": "FA",
      "odd_home_calc": 4.48,
      "odd_away_calc": 1.97,
      "entrada": "AWAY",
      "fthg": 2.0,
      "ftag": 1.0,
      "lp": -1
    },
    {
      "home": "Cagliari",
      "away": "Fiorentina",
      "b365h": 3.3,
      "b365a": 2.3,
      "xgh": 0.87,
      "xga": 1.53,
      "dxg": "LA",
      "odd_home_calc": 4.67,
      "odd_away_calc": 1.91,
      "entrada": "AWAY",
      "fthg": 2.0,
      "ftag": 1.0,
      "lp": -1
    },
    {
      "home": "Sassuolo",
      "away": "Sampdoria",
      "b365h": 2.4,
      "b365a": 3.1,
      "xgh": 0.95,
      "xga": 0.75,
      "dxg": "EQ",
      "odd_home_calc": 2.59,
      "odd_away_calc": 3.63,
      "entrada": "HOME",
      "fthg": 3.0,
      "ftag": 5.0,
      "lp": -1
    },
    {
      "home": "Spal",
      "away": "Roma",
      "b365h": 4.33,
      "b365a": 1.83,
      "xgh": 0.12,
      "xga": 1.55,
      "dxg": "FA",
      "odd_home_calc": 20,
      "odd_away_calc": 1.34,
      "entrada": "AWAY",
      "fthg": 2.0,
      "ftag": 1.0,
      "lp": -1
    },
    {
      "home": "Milan",
      "away": "Inter",
      "b365h": 2.3,
      "b365a": 3.4,
      "xgh": 1.43,
      "xga": 0.48,
      "dxg": "LH",
      "odd_home_calc": 1.66,
      "odd_away_calc": 8.06,
      "entrada": "HOME",
      "fthg": 2.0,
      "ftag": 3.0,
      "lp": -1
    },
    {
      "home": "Empoli",
      "away": "Frosinone",
      "b365h": 1.8,
      "b365a": 4.75,
      "xgh": 2.01,
      "xga": 1.78,
      "dxg": "EQ",
      "odd_home_calc": 2.37,
      "odd_away_calc": 2.95,
      "entrada": "AWAY",
      "fthg": 2.0,
      "ftag": 1.0,
      "lp": -1
    },
    {
      "home": "Genoa",
      "away": "Juventus",
      "b365h": 7.0,
      "b365a": 1.53,
      "xgh": 1.43,
      "xga": 2.36,
      "dxg": "LA",
      "odd_home_calc": 4.52,
      "odd_away_calc": 1.82,
      "entrada": "HOME",
      "fthg": 2.0,
      "ftag": 0.0,
      "lp": 6.0
    },
    {
      "home": "Chievo",
      "away": "Cagliari",
      "b365h": 2.7,
      "b365a": 2.87,
      "xgh": 1.17,
      "xga": 1.0,
      "dxg": "EQ",
      "odd_home_calc": 2.52,
      "odd_away_calc": 3.23,
      "entrada": "HOME",
      "fthg": 0.0,
      "ftag": 3.0,
      "lp": -1
    },
    {
      "home": "Sampdoria",
      "away": "Milan",
      "b365h": 3.25,
      "b365a": 2.37,
      "xgh": 0.15,
      "xga": 1.16,
      "dxg": "FA",
      "odd_home_calc": 20,
      "odd_away_calc": 1.59,
      "entrada": "AWAY",
      "fthg": 1.0,
      "ftag": 0.0,
      "lp": -1
    },
    {
      "home": "Udinese",
      "away": "Genoa",
      "b365h": 2.5,
      "b365a": 3.1,
      "xgh": 0.99,
      "xga": 1.4,
      "dxg": "LA",
      "odd_home_calc": 3.78,
      "odd_away_calc": 2.16,
      "entrada": "AWAY",
      "fthg": 2.0,
      "ftag": 0.0,
      "lp": -1
    },
    {
      "home": "Bologna",
      "away": "Sassuolo",
      "b365h": 2.05,
      "b365a": 3.75,
      "xgh": 1.09,
      "xga": 1.31,
      "dxg": "EQ",
      "odd_home_calc": 3.23,
      "odd_away_calc": 2.42,
      "entrada": "AWAY",
      "fthg": 2.0,
      "ftag": 1.0,
      "lp": -1
    },
    {
      "home": "Fiorentina",
      "away": "Torino",
      "b365h": 2.1,
      "b365a": 3.8,
      "xgh": 1.12,
      "xga": 1.01,
      "dxg": "EQ",
      "odd_home_calc": 2.63,
      "odd_away_calc": 3.11,
      "entrada": "AWAY",
      "fthg": 1.0,
      "ftag": 1.0,
      "lp": -1
    },
    {
      "home": "Frosinone",
      "away": "Spal",
      "b365h": 2.9,
      "b365a": 2.6,
      "xgh": 3.06,
      "xga": 2.02,
      "dxg": "FH",
      "odd_home_calc": 1.99,
      "odd_away_calc": 4.41,
      "entrada": "HOME",
      "fthg": 0.0,
      "ftag": 1.0,
      "lp": -1
    },
    {
      "home": "Inter",
      "away": "Lazio",
      "b365h": 2.25,
      "b365a": 3.3,
      "xgh": 1.06,
      "xga": 0.43,
      "dxg": "LH",
      "odd_home_calc": 1.95,
      "odd_away_calc": 6.79,
      "entrada": "HOME",
      "fthg": 0.0,
      "ftag": 1.0,
      "lp": -1
    },
    {
      "home": "Parma",
      "away": "Atalanta",
      "b365h": 5.75,
      "b365a": 1.6,
      "xgh": 0.09,
      "xga": 3.82,
      "dxg": "FA",
      "odd_home_calc": 20,
      "odd_away_calc": 1.28,
      "entrada": "AWAY",
      "fthg": 1.0,
      "ftag": 3.0,
      "lp": 0.6
    },
    {
      "home": "Roma",
      "away": "Napoli",
      "b365h": 3.1,
      "b365a": 2.3,
      "xgh": 1.04,
      "xga": 1.71,
      "dxg": "LA",
      "odd_home_calc": 4.36,
      "odd_away_calc": 1.91,
      "entrada": "AWAY",
      "fthg": 1.0,
      "ftag": 4.0,
      "lp": 1.3
    },
    {
      "home": "Spal",
      "away": "Lazio",
      "b365h": 5.0,
      "b365a": 1.72,
      "xgh": 0.1,
      "xga": 1.19,
      "dxg": "FA",
      "odd_home_calc": 20,
      "odd_away_calc": 1.52,
      "entrada": "AWAY",
      "fthg": 1.0,
      "ftag": 0.0,
      "lp": -1
    },
    {
      "home": "Roma",
      "away": "Fiorentina",
      "b365h": 2.0,
      "b365a": 3.75,
      "xgh": 1.55,
      "xga": 0.63,
      "dxg": "LH",
      "odd_home_calc": 1.69,
      "odd_away_calc": 6.64,
      "entrada": "HOME",
      "fthg": 2.0,
      "ftag": 2.0,
      "lp": -1
    },
    {
      "home": "Frosinone",
      "away": "Parma",
      "b365h": 2.4,
      "b365a": 3.1,
      "xgh": 0.21,
      "xga": 1.11,
      "dxg": "LA",
      "odd_home_calc": 14.51,
      "odd_away_calc": 1.67,
      "entrada": "AWAY",
      "fthg": 3.0,
      "ftag": 2.0,
      "lp": -1
    },
    {
      "home": "Empoli",
      "away": "Napoli",
      "b365h": 7.0,
      "b365a": 1.44,
      "xgh": 0.07,
      "xga": 2.18,
      "dxg": "FA",
      "odd_home_calc": 20,
      "odd_away_calc": 1.18,
      "entrada": "AWAY",
      "fthg": 2.0,
      "ftag": 1.0,
      "lp": -1
    },
    {
      "home": "Genoa",
      "away": "Inter",
      "b365h": 4.0,
      "b365a": 2.05,
      "xgh": 1.03,
      "xga": 1.36,
      "dxg": "LA",
      "odd_home_calc": 3.53,
      "odd_away_calc": 2.27,
      "entrada": "HOME",
      "fthg": 0.0,
      "ftag": 4.0,
      "lp": -1
    },
    {
      "home": "Juventus",
      "away": "Milan",
      "b365h": 1.75,
      "b365a": 5.25,
      "xgh": 1.67,
      "xga": 1.46,
      "dxg": "EQ",
      "odd_home_calc": 2.39,
      "odd_away_calc": 2.99,
      "entrada": "AWAY",
      "fthg": 2.0,
      "ftag": 1.0,
      "lp": -1
    },
    {
      "home": "Parma",
      "away": "Torino",
      "b365h": 4.0,
      "b365a": 2.0,
      "xgh": 0.58,
      "xga": 2.12,
      "dxg": "FA",
      "odd_home_calc": 11.35,
      "odd_away_calc": 1.41,
      "entrada": "AWAY",
      "fthg": 0.0,
      "ftag": 0.0,
      "lp": -1
    },
    {
      "home": "Sampdoria",
      "away": "Roma",
      "b365h": 2.9,
      "b365a": 2.5,
      "xgh": 1.27,
      "xga": 1.2,
      "dxg": "EQ",
      "odd_home_calc": 2.65,
      "odd_away_calc": 2.88,
      "entrada": "AWAY",
      "fthg": 0.0,
      "ftag": 1.0,
      "lp": 1.5
    },
    {
      "home": "Fiorentina",
      "away": "Frosinone",
      "b365h": 1.5,
      "b365a": 7.5,
      "xgh": 1.55,
      "xga": 1.03,
      "dxg": "LH",
      "odd_home_calc": 2.06,
      "odd_away_calc": 3.96,
      "entrada": "AWAY",
      "fthg": 0.0,
      "ftag": 1.0,
      "lp": 6.5
    },
    {
      "home": "Inter",
      "away": "Atalanta",
      "b365h": 2.0,
      "b365a": 3.9,
      "xgh": 1.75,
      "xga": 0.51,
      "dxg": "FH",
      "odd_home_calc": 1.49,
      "odd_away_calc": 9.88,
      "entrada": "HOME",
      "fthg": 0.0,
      "ftag": 0.0,
      "lp": -1
    },
    {
      "home": "Cagliari",
      "away": "Spal",
      "b365h": 2.15,
      "b365a": 3.6,
      "xgh": 1.49,
      "xga": 1.2,
      "dxg": "EQ",
      "odd_home_calc": 2.3,
      "odd_away_calc": 3.29,
      "entrada": "HOME",
      "fthg": 2.0,
      "ftag": 1.0,
      "lp": 1.15
    },
    {
      "home": "Milan",
      "away": "Lazio",
      "b365h": 2.6,
      "b365a": 2.75,
      "xgh": 1.01,
      "xga": 1.21,
      "dxg": "EQ",
      "odd_home_calc": 3.25,
      "odd_away_calc": 2.48,
      "entrada": "AWAY",
      "fthg": 1.0,
      "ftag": 0.0,
      "lp": -1
    },
    {
      "home": "Roma",
      "away": "Udinese",
      "b365h": 1.44,
      "b365a": 7.0,
      "xgh": 1.94,
      "xga": 0.18,
      "dxg": "FH",
      "odd_home_calc": 1.26,
      "odd_away_calc": 20,
      "entrada": "HOME",
      "fthg": 1.0,
      "ftag": 0.0,
      "lp": 0.44
    },
    {
      "home": "Spal",
      "away": "Juventus",
      "b365h": 4.0,
      "b365a": 2.05,
      "xgh": 1.43,
      "xga": 1.22,
      "dxg": "EQ",
      "odd_home_calc": 2.4,
      "odd_away_calc": 3.14,
      "entrada": "HOME",
      "fthg": 2.0,
      "ftag": 1.0,
      "lp": 3.0
    },
    {
      "home": "Sassuolo",
      "away": "Parma",
      "b365h": 1.66,
      "b365a": 5.0,
      "xgh": 1.99,
      "xga": 0.65,
      "dxg": "FH",
      "odd_home_calc": 1.48,
      "odd_away_calc": 8.98,
      "entrada": "HOME",
      "fthg": 0.0,
      "ftag": 0.0,
      "lp": -1
    },
    {
      "home": "Sampdoria",
      "away": "Genoa",
      "b365h": 2.4,
      "b365a": 3.2,
      "xgh": 0.98,
      "xga": 1.07,
      "dxg": "EQ",
      "odd_home_calc": 3.07,
      "odd_away_calc": 2.71,
      "entrada": "AWAY",
      "fthg": 2.0,
      "ftag": 0.0,
      "lp": -1
    },
    {
      "home": "Torino",
      "away": "Cagliari",
      "b365h": 1.85,
      "b365a": 4.75,
      "xgh": 1.67,
      "xga": 0.39,
      "dxg": "FH",
      "odd_home_calc": 1.46,
      "odd_away_calc": 12.39,
      "entrada": "HOME",
      "fthg": 1.0,
      "ftag": 1.0,
      "lp": -1
    },
    {
      "home": "Atalanta",
      "away": "Empoli",
      "b365h": 1.33,
      "b365a": 9.0,
      "xgh": 1.76,
      "xga": 0.69,
      "dxg": "FH",
      "odd_home_calc": 1.61,
      "odd_away_calc": 7.07,
      "entrada": "AWAY",
      "fthg": 0.0,
      "ftag": 0.0,
      "lp": -1
    },
    {
      "home": "Lazio",
      "away": "Udinese",
      "b365h": 1.36,
      "b365a": 8.5,
      "xgh": 1.94,
      "xga": 0.82,
      "dxg": "FH",
      "odd_home_calc": 1.6,
      "odd_away_calc": 6.65,
      "entrada": "AWAY",
      "fthg": 2.0,
      "ftag": 0.0,
      "lp": -1
    },
    {
      "home": "Empoli",
      "away": "Spal",
      "b365h": 2.15,
      "b365a": 3.6,
      "xgh": 1.0,
      "xga": 1.15,
      "dxg": "EQ",
      "odd_home_calc": 3.17,
      "odd_away_calc": 2.57,
      "entrada": "AWAY",
      "fthg": 2.0,
      "ftag": 4.0,
      "lp": 2.6
    },
    {
      "home": "Genoa",
      "away": "Torino",
      "b365h": 2.75,
      "b365a": 2.87,
      "xgh": 1.69,
      "xga": 1.68,
      "dxg": "EQ",
      "odd_home_calc": 2.63,
      "odd_away_calc": 2.65,
      "entrada": "HOME",
      "fthg": 0.0,
      "ftag": 1.0,
      "lp": -1
    },
    {
      "home": "Inter",
      "away": "Roma",
      "b365h": 1.8,
      "b365a": 4.5,
      "xgh": 1.64,
      "xga": 0.57,
      "dxg": "FH",
      "odd_home_calc": 1.59,
      "odd_away_calc": 7.94,
      "entrada": "HOME",
      "fthg": 1.0,
      "ftag": 1.0,
      "lp": -1
    },
    {
      "home": "Juventus",
      "away": "Fiorentina",
      "b365h": 1.4,
      "b365a": 9.0,
      "xgh": 2.1,
      "xga": 0.06,
      "dxg": "FH",
      "odd_home_calc": 1.19,
      "odd_away_calc": 20,
      "entrada": "HOME",
      "fthg": 2.0,
      "ftag": 1.0,
      "lp": 0.4
    },
    {
      "home": "Napoli",
      "away": "Atalanta",
      "b365h": 1.85,
      "b365a": 4.2,
      "xgh": 3.1,
      "xga": 0.79,
      "dxg": "FH",
      "odd_home_calc": 1.37,
      "odd_away_calc": 15.97,
      "entrada": "HOME",
      "fthg": 1.0,
      "ftag": 2.0,
      "lp": -1
    },
    {
      "home": "Udinese",
      "away": "Sassuolo",
      "b365h": 2.35,
      "b365a": 3.2,
      "xgh": 1.37,
      "xga": 0.74,
      "dxg": "LH",
      "odd_home_calc": 1.94,
      "odd_away_calc": 4.95,
      "entrada": "HOME",
      "fthg": 1.0,
      "ftag": 1.0,
      "lp": -1
    },
    {
      "home": "Napoli",
      "away": "Atalanta",
      "b365h": 1.85,
      "b365a": 4.2,
      "xgh": 2.57,
      "xga": 0.87,
      "dxg": "FH",
      "odd_home_calc": 1.44,
      "odd_away_calc": 9.58,
      "entrada": "HOME",
      "fthg": 1.0,
      "ftag": 2.0,
      "lp": -1
    },
    {
      "home": "Roma",
      "away": "Cagliari",
      "b365h": 1.4,
      "b365a": 8.0,
      "xgh": 2.05,
      "xga": 0.83,
      "dxg": "FH",
      "odd_home_calc": 1.56,
      "odd_away_calc": 7.08,
      "entrada": "AWAY",
      "fthg": 3.0,
      "ftag": 0.0,
      "lp": -1
    },
    {
      "home": "Inter",
      "away": "Juventus",
      "b365h": 2.37,
      "b365a": 2.9,
      "xgh": 0.99,
      "xga": 0.99,
      "dxg": "EQ",
      "odd_home_calc": 2.9,
      "odd_away_calc": 2.91,
      "entrada": "HOME",
      "fthg": 1.0,
      "ftag": 1.0,
      "lp": -1
    },
    {
      "home": "Sampdoria",
      "away": "Lazio",
      "b365h": 3.0,
      "b365a": 2.3,
      "xgh": 1.13,
      "xga": 1.3,
      "dxg": "EQ",
      "odd_home_calc": 3.11,
      "odd_away_calc": 2.49,
      "entrada": "AWAY",
      "fthg": 1.0,
      "ftag": 2.0,
      "lp": 1.3
    },
    {
      "home": "Spal",
      "away": "Genoa",
      "b365h": 2.5,
      "b365a": 3.4,
      "xgh": 1.01,
      "xga": 0.86,
      "dxg": "EQ",
      "odd_home_calc": 2.63,
      "odd_away_calc": 3.35,
      "entrada": "HOME",
      "fthg": 1.0,
      "ftag": 1.0,
      "lp": -1
    },
    {
      "home": "Torino",
      "away": "Milan",
      "b365h": 2.75,
      "b365a": 2.55,
      "xgh": 0.68,
      "xga": 1.25,
      "dxg": "LA",
      "odd_home_calc": 4.97,
      "odd_away_calc": 2.0,
      "entrada": "AWAY",
      "fthg": 2.0,
      "ftag": 0.0,
      "lp": -1
    },
    {
      "home": "Fiorentina",
      "away": "Sassuolo",
      "b365h": 1.72,
      "b365a": 5.0,
      "xgh": 1.68,
      "xga": 1.26,
      "dxg": "LH",
      "odd_home_calc": 2.15,
      "odd_away_calc": 3.51,
      "entrada": "AWAY",
      "fthg": 0.0,
      "ftag": 1.0,
      "lp": 4.0
    },
    {
      "home": "Chievo",
      "away": "Spal",
      "b365h": 3.2,
      "b365a": 2.45,
      "xgh": 0.42,
      "xga": 2.86,
      "dxg": "FA",
      "odd_home_calc": 20,
      "odd_away_calc": 1.25,
      "entrada": "AWAY",
      "fthg": 0.0,
      "ftag": 4.0,
      "lp": 1.45
    },
    {
      "home": "Parma",
      "away": "Sampdoria",
      "b365h": 3.0,
      "b365a": 2.45,
      "xgh": 1.24,
      "xga": 0.91,
      "dxg": "LH",
      "odd_home_calc": 2.29,
      "odd_away_calc": 3.7,
      "entrada": "HOME",
      "fthg": 3.0,
      "ftag": 3.0,
      "lp": -1
    },
    {
      "home": "Genoa",
      "away": "Roma",
      "b365h": 3.75,
      "b365a": 2.0,
      "xgh": 0.87,
      "xga": 0.99,
      "dxg": "EQ",
      "odd_home_calc": 3.26,
      "odd_away_calc": 2.69,
      "entrada": "HOME",
      "fthg": 1.0,
      "ftag": 1.0,
      "lp": -1
    },
    {
      "home": "Lazio",
      "away": "Bologna",
      "b365h": 2.1,
      "b365a": 3.8,
      "xgh": 2.33,
      "xga": 0.48,
      "dxg": "FH",
      "odd_home_calc": 1.32,
      "odd_away_calc": 16.63,
      "entrada": "HOME",
      "fthg": 3.0,
      "ftag": 3.0,
      "lp": -1
    },
    {
      "home": "Empoli",
      "away": "Fiorentina",
      "b365h": 2.3,
      "b365a": 3.0,
      "xgh": 0.87,
      "xga": 0.86,
      "dxg": "EQ",
      "odd_home_calc": 2.98,
      "odd_away_calc": 3.06,
      "entrada": "HOME",
      "fthg": 1.0,
      "ftag": 0.0,
      "lp": 1.3
    },
    {
      "home": "Genoa",
      "away": "Roma",
      "b365h": 3.75,
      "b365a": 2.0,
      "xgh": 0.88,
      "xga": 0.99,
      "dxg": "EQ",
      "odd_home_calc": 3.25,
      "odd_away_calc": 2.7,
      "entrada": "HOME",
      "fthg": 1.0,
      "ftag": 1.0,
      "lp": -1
    },
    {
      "home": "Torino",
      "away": "Sassuolo",
      "b365h": 1.53,
      "b365a": 5.75,
      "xgh": 1.14,
      "xga": 0.77,
      "dxg": "LH",
      "odd_home_calc": 2.26,
      "odd_away_calc": 4.06,
      "entrada": "AWAY",
      "fthg": 3.0,
      "ftag": 2.0,
      "lp": -1
    },
    {
      "home": "Sampdoria",
      "away": "Juventus",
      "b365h": 3.8,
      "b365a": 1.85,
      "xgh": 1.0,
      "xga": 1.0,
      "dxg": "EQ",
      "odd_home_calc": 2.9,
      "odd_away_calc": 2.89,
      "entrada": "HOME",
      "fthg": 2.0,
      "ftag": 0.0,
      "lp": 2.8
    },
    {
      "home": "Frosinone",
      "away": "Udinese",
      "b365h": 5.0,
      "b365a": 1.75,
      "xgh": 0.67,
      "xga": 3.0,
      "dxg": "FA",
      "odd_home_calc": 18.57,
      "odd_away_calc": 1.33,
      "entrada": "AWAY",
      "fthg": 1.0,
      "ftag": 3.0,
      "lp": 0.75
    },
    {
      "home": "Roma",
      "away": "Juventus",
      "b365h": 2.5,
      "b365a": 2.75,
      "xgh": 1.47,
      "xga": 0.52,
      "dxg": "LH",
      "odd_home_calc": 1.66,
      "odd_away_calc": 7.63,
      "entrada": "HOME",
      "fthg": 2.0,
      "ftag": 0.0,
      "lp": 1.5
    },
    {
      "home": "Sampdoria",
      "away": "Empoli",
      "b365h": 2.37,
      "b365a": 2.87,
      "xgh": 0.88,
      "xga": 1.28,
      "dxg": "LA",
      "odd_home_calc": 3.92,
      "odd_away_calc": 2.2,
      "entrada": "AWAY",
      "fthg": 1.0,
      "ftag": 2.0,
      "lp": 1.87
    },
    {
      "home": "Torino",
      "away": "Lazio",
      "b365h": 2.15,
      "b365a": 3.0,
      "xgh": 1.08,
      "xga": 0.37,
      "dxg": "LH",
      "odd_home_calc": 1.87,
      "odd_away_calc": 7.92,
      "entrada": "HOME",
      "fthg": 3.0,
      "ftag": 1.0,
      "lp": 1.15
    },
    {
      "home": "Empoli",
      "away": "Torino",
      "b365h": 2.55,
      "b365a": 2.62,
      "xgh": 2.05,
      "xga": 1.47,
      "dxg": "LH",
      "odd_home_calc": 2.03,
      "odd_away_calc": 3.68,
      "entrada": "HOME",
      "fthg": 4.0,
      "ftag": 1.0,
      "lp": 1.55
    },
    {
      "home": "Napoli",
      "away": "Inter",
      "b365h": 2.45,
      "b365a": 2.75,
      "xgh": 1.93,
      "xga": 0.89,
      "dxg": "FH",
      "odd_home_calc": 1.66,
      "odd_away_calc": 6.0,
      "entrada": "HOME",
      "fthg": 4.0,
      "ftag": 1.0,
      "lp": 1.45
    },
    {
      "home": "Parma",
      "away": "Fiorentina",
      "b365h": 3.1,
      "b365a": 2.37,
      "xgh": 1.37,
      "xga": 1.29,
      "dxg": "EQ",
      "odd_home_calc": 2.6,
      "odd_away_calc": 2.86,
      "entrada": "HOME",
      "fthg": 1.0,
      "ftag": 0.0,
      "lp": 2.1
    },
    {
      "home": "Lazio",
      "away": "Bologna",
      "b365h": 2.1,
      "b365a": 3.8,
      "xgh": 2.37,
      "xga": 0.55,
      "dxg": "FH",
      "odd_home_calc": 1.34,
      "odd_away_calc": 14.55,
      "entrada": "HOME",
      "fthg": 3.0,
      "ftag": 3.0,
      "lp": -1
    },
    {
      "home": "Cagliari",
      "away": "Udinese",
      "b365h": 2.25,
      "b365a": 3.0,
      "xgh": 2.05,
      "xga": 0.88,
      "dxg": "FH",
      "odd_home_calc": 1.6,
      "odd_away_calc": 6.58,
      "entrada": "HOME",
      "fthg": 1.0,
      "ftag": 2.0,
      "lp": -1
    },
    {
      "home": "Frosinone",
      "away": "Chievo",
      "b365h": 2.2,
      "b365a": 3.0,
      "xgh": 1.94,
      "xga": 4.05,
      "dxg": "FA",
      "odd_home_calc": 7.98,
      "odd_away_calc": 1.91,
      "entrada": "AWAY",
      "fthg": 0.0,
      "ftag": 0.0,
      "lp": -1
    },
    {
      "home": "Sampdoria",
      "away": "Juventus",
      "b365h": 3.8,
      "b365a": 1.85,
      "xgh": 1.43,
      "xga": 0.59,
      "dxg": "LH",
      "odd_home_calc": 1.75,
      "odd_away_calc": 6.46,
      "entrada": "HOME",
      "fthg": 2.0,
      "ftag": 0.0,
      "lp": 2.8
    },
    {
      "home": "Spal",
      "away": "Milan",
      "b365h": 6.5,
      "b365a": 1.44,
      "xgh": 1.97,
      "xga": 3.0,
      "dxg": "FA",
      "odd_home_calc": 4.39,
      "odd_away_calc": 1.97,
      "entrada": "HOME",
      "fthg": 2.0,
      "ftag": 3.0,
      "lp": -1
    },
    {
      "home": "Cagliari",
      "away": "Udinese",
      "b365h": 2.25,
      "b365a": 3.0,
      "xgh": 1.91,
      "xga": 0.92,
      "dxg": "LH",
      "odd_home_calc": 1.69,
      "odd_away_calc": 5.71,
      "entrada": "HOME",
      "fthg": 1.0,
      "ftag": 2.0,
      "lp": -1
    },
    {
      "home": "Atalanta",
      "away": "Sassuolo",
      "b365h": 1.2,
      "b365a": 11.0,
      "xgh": 2.5,
      "xga": 1.0,
      "dxg": "FH",
      "odd_home_calc": 1.52,
      "odd_away_calc": 7.63,
      "entrada": "AWAY",
      "fthg": 3.0,
      "ftag": 1.0,
      "lp": -1
    },
    {
      "home": "Torino",
      "away": "Lazio",
      "b365h": 2.15,
      "b365a": 3.0,
      "xgh": 1.34,
      "xga": 0.49,
      "dxg": "LH",
      "odd_home_calc": 1.73,
      "odd_away_calc": 7.34,
      "entrada": "HOME",
      "fthg": 3.0,
      "ftag": 1.0,
      "lp": 1.15
    }
  ],
  "lucro_total": -7.139999999999999,
  "acertos": 85,
  "erros": 156,
  "total_jogos": 380,
  "completo": true
}