{
  "rodada_atual": 37,
  "jogos_processados": 306,
  "entradas": [
    {
      "home": "Hamburg",
      "away": "Hannover",
      "b365h": 2.0,
      "b365a": 4.0,
      "xgh": 0.94,
      "xga": 0.93,
      "dxg": "EQ",
      "odd_home_calc": 2.93,
      "odd_away_calc": 2.97,
      "entrada": "AWAY",
      "fthg": 1,
      "ftag": 2,
      "lp": 3.0
    },
    {
      "home": "Leverkusen",
      "away": "Augsburg",
      "b365h": 1.4,
      "b365a": 8.0,
      "xgh": 2.27,
      "xga": 1.05,
      "dxg": "FH",
      "odd_home_calc": 1.61,
      "odd_away_calc": 6.21,
      "entrada": "AWAY",
      "fthg": 1,
      "ftag": 1,
      "lp": -1
    },
    {
      "home": "Schalke 04",
      "away": "FC Koln",
      "b365h": 1.73,
      "b365a": 4.8,
      "xgh": 1.43,
      "xga": 1.9,
      "dxg": "LA",
      "odd_home_calc": 3.48,
      "odd_away_calc": 2.11,
      "entrada": "AWAY",
      "fthg": 0,
      "ftag": 3,
      "lp": 3.8
    },
    {
      "home": "Bayern Munich",
      "away": "Dortmund",
      "b365h": 1.5,
      "b365a": 6.5,
      "xgh": 1.96,
      "xga": 1.02,
      "dxg": "LH",
      "odd_home_calc": 1.73,
      "odd_away_calc": 5.23,
      "entrada": "AWAY",
      "fthg": 5,
      "ftag": 1,
      "lp": -1
    },
    {
      "home": "Hertha",
      "away": "Werder Bremen",
      "b365h": 2.05,
      "b365a": 3.6,
      "xgh": 1.03,
      "xga": 1.33,
      "dxg": "EQ",
      "odd_home_calc": 3.46,
      "odd_away_calc": 2.31,
      "entrada": "AWAY",
      "fthg": 1,
      "ftag": 1,
      "lp": -1
    },
    {
      "home": "Mainz",
      "away": "Hoffenheim",
      "b365h": 2.15,
      "b365a": 3.3,
      "xgh": 1.05,
      "xga": 0.91,
      "dxg": "EQ",
      "odd_home_calc": 2.63,
      "odd_away_calc": 3.26,
      "entrada": "HOME",
      "fthg": 3,
      "ftag": 1,
      "lp": 1.15
    },
    {
      "home": "Schalke 04",
      "away": "FC Koln",
      "b365h": 1.73,
      "b365a": 4.8,
      "xgh": 1.28,
      "xga": 2.38,
      "dxg": "FA",
      "odd_home_calc": 5.24,
      "odd_away_calc": 1.71,
      "entrada": "AWAY",
      "fthg": 0,
      "ftag": 3,
      "lp": 3.8
    },
    {
      "home": "Hamburg",
      "away": "Mainz",
      "b365h": 2.25,
      "b365a": 3.2,
      "xgh": 0.99,
      "xga": 1.39,
      "dxg": "LA",
      "odd_home_calc": 3.74,
      "odd_away_calc": 2.18,
      "entrada": "AWAY",
      "fthg": 1,
      "ftag": 3,
      "lp": 2.2
    },
    {
      "home": "Stuttgart",
      "away": "Werder Bremen",
      "b365h": 1.95,
      "b365a": 3.75,
      "xgh": 0.99,
      "xga": 1.31,
      "dxg": "LA",
      "odd_home_calc": 3.57,
      "odd_away_calc": 2.28,
      "entrada": "AWAY",
      "fthg": 1,
      "ftag": 1,
      "lp": -1
    },
    {
      "home": "Augsburg",
      "away": "Hannover",
      "b365h": 2.0,
      "b365a": 3.75,
      "xgh": 1.31,
      "xga": 1.02,
      "dxg": "EQ",
      "odd_home_calc": 2.32,
      "odd_away_calc": 3.45,
      "entrada": "HOME",
      "fthg": 2,
      "ftag": 0,
      "lp": 1.0
    },
    {
      "home": "Hannover",
      "away": "Hertha",
      "b365h": 2.63,
      "b365a": 2.7,
      "xgh": 2.54,
      "xga": 1.81,
      "dxg": "LH",
      "odd_home_calc": 2.02,
      "odd_away_calc": 3.81,
      "entrada": "HOME",
      "fthg": 1,
      "ftag": 3,
      "lp": -1
    },
    {
      "home": "Ein Frankfurt",
      "away": "Darmstadt",
      "b365h": 1.91,
      "b365a": 4.33,
      "xgh": 1.02,
      "xga": 1.0,
      "dxg": "EQ",
      "odd_home_calc": 2.86,
      "odd_away_calc": 2.93,
      "entrada": "AWAY",
      "fthg": 0,
      "ftag": 1,
      "lp": 3.33
    },
    {
      "home": "Stuttgart",
      "away": "Werder Bremen",
      "b365h": 1.95,
      "b365a": 3.75,
      "xgh": 0.99,
      "xga": 1.29,
      "dxg": "EQ",
      "odd_home_calc": 3.51,
      "odd_away_calc": 2.32,
      "entrada": "AWAY",
      "fthg": 1,
      "ftag": 1,
      "lp": -1
    },
    {
      "home": "Mainz",
      "away": "Wolfsburg",
      "b365h": 3.3,
      "b365a": 2.15,
      "xgh": 1.19,
      "xga": 1.46,
      "dxg": "EQ",
      "odd_home_calc": 3.26,
      "odd_away_calc": 2.33,
      "entrada": "AWAY",
      "fthg": 2,
      "ftag": 0,
      "lp": -1
    },
    {
      "home": "Augsburg",
      "away": "Hoffenheim",
      "b365h": 2.25,
      "b365a": 3.1,
      "xgh": 1.28,
      "xga": 1.32,
      "dxg": "EQ",
      "odd_home_calc": 2.81,
      "odd_away_calc": 2.66,
      "entrada": "AWAY",
      "fthg": 1,
      "ftag": 3,
      "lp": 2.1
    },
    {
      "home": "Augsburg",
      "away": "Werder Bremen",
      "b365h": 2.2,
      "b365a": 3.3,
      "xgh": 1.46,
      "xga": 1.4,
      "dxg": "EQ",
      "odd_home_calc": 2.61,
      "odd_away_calc": 2.78,
      "entrada": "AWAY",
      "fthg": 1,
      "ftag": 2,
      "lp": 2.3
    },
    {
      "home": "Dortmund",
      "away": "Schalke 04",
      "b365h": 1.3,
      "b365a": 8.5,
      "xgh": 2.0,
      "xga": 2.0,
      "dxg": "EQ",
      "odd_home_calc": 2.64,
      "odd_away_calc": 2.63,
      "entrada": "AWAY",
      "fthg": 3,
      "ftag": 2,
      "lp": -1
    },
    {
      "home": "Bayern Munich",
      "away": "Hamburg",
      "b365h": 1.08,
      "b365a": 29.0,
      "xgh": 3.18,
      "xga": 0.02,
      "dxg": "FH",
      "odd_home_calc": 1.17,
      "odd_away_calc": 20,
      "entrada": "AWAY",
      "fthg": 5,
      "ftag": 0,
      "lp": -1
    },
    {
      "home": "Leverkusen",
      "away": "Hoffenheim",
      "b365h": 1.5,
      "b365a": 6.5,
      "xgh": 2.76,
      "xga": 0.08,
      "dxg": "FH",
      "odd_home_calc": 1.16,
      "odd_away_calc": 20,
      "entrada": "HOME",
      "fthg": 2,
      "ftag": 1,
      "lp": 0.5
    },
    {
      "home": "Stuttgart",
      "away": "FC Koln",
      "b365h": 2.05,
      "b365a": 3.8,
      "xgh": 0.87,
      "xga": 0.71,
      "dxg": "EQ",
      "odd_home_calc": 2.71,
      "odd_away_calc": 3.62,
      "entrada": "HOME",
      "fthg": 1,
      "ftag": 3,
      "lp": -1
    },
    {
      "home": "Hertha",
      "away": "Werder Bremen",
      "b365h": 2.05,
      "b365a": 3.6,
      "xgh": 1.03,
      "xga": 1.22,
      "dxg": "EQ",
      "odd_home_calc": 3.23,
      "odd_away_calc": 2.49,
      "entrada": "AWAY",
      "fthg": 1,
      "ftag": 1,
      "lp": -1
    },
    {
      "home": "Hamburg",
      "away": "Augsburg",
      "b365h": 2.4,
      "b365a": 3.0,
      "xgh": 1.02,
      "xga": 0.93,
      "dxg": "EQ",
      "odd_home_calc": 2.74,
      "odd_away_calc": 3.12,
      "entrada": "HOME",
      "fthg": 0,
      "ftag": 1,
      "lp": -1
    },
    {
      "home": "Ingolstadt",
      "away": "Dortmund",
      "b365h": 7.0,
      "b365a": 1.45,
      "xgh": 0.07,
      "xga": 2.12,
      "dxg": "FA",
      "odd_home_calc": 20,
      "odd_away_calc": 1.19,
      "entrada": "AWAY",
      "fthg": 0,
      "ftag": 4,
      "lp": 0.45
    },
    {
      "home": "M'gladbach",
      "away": "Mainz",
      "b365h": 1.67,
      "b365a": 5.0,
      "xgh": 1.46,
      "xga": 0.92,
      "dxg": "LH",
      "odd_home_calc": 2.03,
      "odd_away_calc": 4.22,
      "entrada": "AWAY",
      "fthg": 1,
      "ftag": 2,
      "lp": 4.0
    },
    {
      "home": "Wolfsburg",
      "away": "Schalke 04",
      "b365h": 2.0,
      "b365a": 3.5,
      "xgh": 1.18,
      "xga": 1.92,
      "dxg": "LA",
      "odd_home_calc": 4.34,
      "odd_away_calc": 1.88,
      "entrada": "AWAY",
      "fthg": 3,
      "ftag": 0,
      "lp": -1
    },
    {
      "home": "Stuttgart",
      "away": "Ein Frankfurt",
      "b365h": 1.95,
      "b365a": 3.8,
      "xgh": 1.0,
      "xga": 0.89,
      "dxg": "EQ",
      "odd_home_calc": 2.72,
      "odd_away_calc": 3.2,
      "entrada": "AWAY",
      "fthg": 1,
      "ftag": 4,
      "lp": 2.8
    },
    {
      "home": "Werder Bremen",
      "away": "Hertha",
      "b365h": 2.5,
      "b365a": 2.8,
      "xgh": 1.12,
      "xga": 0.72,
      "dxg": "LH",
      "odd_home_calc": 2.22,
      "odd_away_calc": 4.25,
      "entrada": "HOME",
      "fthg": 3,
      "ftag": 3,
      "lp": -1
    },
    {
      "home": "Werder Bremen",
      "away": "M'gladbach",
      "b365h": 3.2,
      "b365a": 2.25,
      "xgh": 0.98,
      "xga": 1.97,
      "dxg": "LA",
      "odd_home_calc": 5.47,
      "odd_away_calc": 1.7,
      "entrada": "AWAY",
      "fthg": 2,
      "ftag": 1,
      "lp": -1
    },
    {
      "home": "Hamburg",
      "away": "Ein Frankfurt",
      "b365h": 2.5,
      "b365a": 2.75,
      "xgh": 1.24,
      "xga": 1.27,
      "dxg": "EQ",
      "odd_home_calc": 2.81,
      "odd_away_calc": 2.69,
      "entrada": "HOME",
      "fthg": 0,
      "ftag": 0,
      "lp": -1
    },
    {
      "home": "FC Koln",
      "away": "Ingolstadt",
      "b365h": 2.05,
      "b365a": 3.8,
      "xgh": 0.24,
      "xga": 0.99,
      "dxg": "LA",
      "odd_home_calc": 11.13,
      "odd_away_calc": 1.84,
      "entrada": "AWAY",
      "fthg": 1,
      "ftag": 1,
      "lp": -1
    },
    {
      "home": "Stuttgart",
      "away": "Schalke 04",
      "b365h": 2.63,
      "b365a": 2.6,
      "xgh": 2.11,
      "xga": 0.96,
      "dxg": "FH",
      "odd_home_calc": 1.62,
      "odd_away_calc": 6.16,
      "entrada": "HOME",
      "fthg": 0,
      "ftag": 1,
      "lp": -1
    },
    {
      "home": "Hertha",
      "away": "FC Koln",
      "b365h": 2.38,
      "b365a": 3.1,
      "xgh": 0.48,
      "xga": 0.8,
      "dxg": "LA",
      "odd_home_calc": 4.94,
      "odd_away_calc": 2.5,
      "entrada": "AWAY",
      "fthg": 2,
      "ftag": 0,
      "lp": -1
    },
    {
      "home": "Wolfsburg",
      "away": "Hoffenheim",
      "b365h": 1.62,
      "b365a": 5.0,
      "xgh": 2.27,
      "xga": 2.0,
      "dxg": "EQ",
      "odd_home_calc": 2.36,
      "odd_away_calc": 3.0,
      "entrada": "AWAY",
      "fthg": 4,
      "ftag": 2,
      "lp": -1
    },
    {
      "home": "Ein Frankfurt",
      "away": "M'gladbach",
      "b365h": 2.45,
      "b365a": 2.88,
      "xgh": 1.37,
      "xga": 1.12,
      "dxg": "EQ",
      "odd_home_calc": 2.37,
      "odd_away_calc": 3.27,
      "entrada": "HOME",
      "fthg": 1,
      "ftag": 5,
      "lp": -1
    },
    {
      "home": "Mainz",
      "away": "Werder Bremen",
      "b365h": 2.05,
      "b365a": 3.6,
      "xgh": 1.21,
      "xga": 1.19,
      "dxg": "EQ",
      "odd_home_calc": 2.75,
      "odd_away_calc": 2.81,
      "entrada": "AWAY",
      "fthg": 1,
      "ftag": 3,
      "lp": 2.6
    },
    {
      "home": "Schalke 04",
      "away": "Ein Frankfurt",
      "b365h": 1.83,
      "b365a": 4.2,
      "xgh": 1.42,
      "xga": 1.6,
      "dxg": "EQ",
      "odd_home_calc": 2.98,
      "odd_away_calc": 2.42,
      "entrada": "AWAY",
      "fthg": 2,
      "ftag": 0,
      "lp": -1
    },
    {
      "home": "M'gladbach",
      "away": "Augsburg",
      "b365h": 2.15,
      "b365a": 3.4,
      "xgh": 1.79,
      "xga": 0.96,
      "dxg": "LH",
      "odd_home_calc": 1.79,
      "odd_away_calc": 4.98,
      "entrada": "HOME",
      "fthg": 4,
      "ftag": 2,
      "lp": 1.15
    },
    {
      "home": "Hannover",
      "away": "Stuttgart",
      "b365h": 2.88,
      "b365a": 2.4,
      "xgh": 1.95,
      "xga": 0.53,
      "dxg": "FH",
      "odd_home_calc": 1.43,
      "odd_away_calc": 10.97,
      "entrada": "HOME",
      "fthg": 1,
      "ftag": 3,
      "lp": -1
    },
    {
      "home": "FC Koln",
      "away": "Ingolstadt",
      "b365h": 2.05,
      "b365a": 3.8,
      "xgh": 0.58,
      "xga": 1.0,
      "dxg": "LA",
      "odd_home_calc": 4.8,
      "odd_away_calc": 2.24,
      "entrada": "AWAY",
      "fthg": 1,
      "ftag": 1,
      "lp": -1
    },
    {
      "home": "Werder Bremen",
      "away": "Leverkusen",
      "b365h": 3.8,
      "b365a": 1.95,
      "xgh": 0.97,
      "xga": 2.5,
      "dxg": "FA",
      "odd_home_calc": 7.89,
      "odd_away_calc": 1.51,
      "entrada": "AWAY",
      "fthg": 0,
      "ftag": 3,
      "lp": 0.95
    },
    {
      "home": "Werder Bremen",
      "away": "Leverkusen",
      "b365h": 3.8,
      "b365a": 1.95,
      "xgh": 0.46,
      "xga": 2.56,
      "dxg": "FA",
      "odd_home_calc": 20,
      "odd_away_calc": 1.28,
      "entrada": "AWAY",
      "fthg": 0,
      "ftag": 3,
      "lp": 0.95
    },
    {
      "home": "Hoffenheim",
      "away": "Hamburg",
      "b365h": 2.1,
      "b365a": 3.4,
      "xgh": 1.64,
      "xga": 0.38,
      "dxg": "FH",
      "odd_home_calc": 1.46,
      "odd_away_calc": 12.48,
      "entrada": "HOME",
      "fthg": 0,
      "ftag": 1,
      "lp": -1
    },
    {
      "home": "M'gladbach",
      "away": "Schalke 04",
      "b365h": 2.15,
      "b365a": 3.3,
      "xgh": 1.69,
      "xga": 1.94,
      "dxg": "EQ",
      "odd_home_calc": 2.99,
      "odd_away_calc": 2.35,
      "entrada": "AWAY",
      "fthg": 3,
      "ftag": 1,
      "lp": -1
    },
    {
      "home": "Augsburg",
      "away": "Mainz",
      "b365h": 2.3,
      "b365a": 3.1,
      "xgh": 1.22,
      "xga": 1.35,
      "dxg": "EQ",
      "odd_home_calc": 2.99,
      "odd_away_calc": 2.53,
      "entrada": "AWAY",
      "fthg": 3,
      "ftag": 3,
      "lp": -1
    },
    {
      "home": "Ein Frankfurt",
      "away": "M'gladbach",
      "b365h": 2.45,
      "b365a": 2.88,
      "xgh": 1.32,
      "xga": 1.34,
      "dxg": "EQ",
      "odd_home_calc": 2.75,
      "odd_away_calc": 2.69,
      "entrada": "HOME",
      "fthg": 1,
      "ftag": 5,
      "lp": -1
    },
    {
      "home": "FC Koln",
      "away": "Hannover",
      "b365h": 1.95,
      "b365a": 4.0,
      "xgh": 0.61,
      "xga": 0.64,
      "dxg": "EQ",
      "odd_home_calc": 3.52,
      "odd_away_calc": 3.26,
      "entrada": "AWAY",
      "fthg": 0,
      "ftag": 1,
      "lp": 3.0
    },
    {
      "home": "Stuttgart",
      "away": "Ingolstadt",
      "b365h": 1.8,
      "b365a": 4.33,
      "xgh": 1.43,
      "xga": 0.12,
      "dxg": "FH",
      "odd_home_calc": 1.39,
      "odd_away_calc": 20,
      "entrada": "HOME",
      "fthg": 1,
      "ftag": 0,
      "lp": 0.8
    },
    {
      "home": "Hoffenheim",
      "away": "Hamburg",
      "b365h": 2.1,
      "b365a": 3.4,
      "xgh": 1.33,
      "xga": 0.42,
      "dxg": "LH",
      "odd_home_calc": 1.68,
      "odd_away_calc": 8.48,
      "entrada": "HOME",
      "fthg": 0,
      "ftag": 1,
      "lp": -1
    },
    {
      "home": "Mainz",
      "away": "Werder Bremen",
      "b365h": 2.05,
      "b365a": 3.6,
      "xgh": 1.19,
      "xga": 1.32,
      "dxg": "EQ",
      "odd_home_calc": 2.99,
      "odd_away_calc": 2.55,
      "entrada": "AWAY",
      "fthg": 1,
      "ftag": 3,
      "lp": 2.6
    },
    {
      "home": "Wolfsburg",
      "away": "Leverkusen",
      "b365h": 2.63,
      "b365a": 2.7,
      "xgh": 1.44,
      "xga": 2.06,
      "dxg": "LA",
      "odd_home_calc": 3.79,
      "odd_away_calc": 2.0,
      "entrada": "AWAY",
      "fthg": 2,
      "ftag": 1,
      "lp": -1
    },
    {
      "home": "Darmstadt",
      "away": "Wolfsburg",
      "b365h": 4.75,
      "b365a": 1.75,
      "xgh": 0.11,
      "xga": 2.05,
      "dxg": "FA",
      "odd_home_calc": 20,
      "odd_away_calc": 1.21,
      "entrada": "AWAY",
      "fthg": 0,
      "ftag": 1,
      "lp": 0.75
    },
    {
      "home": "Bayern Munich",
      "away": "FC Koln",
      "b365h": 1.1,
      "b365a": 29.0,
      "xgh": 3.71,
      "xga": 0.02,
      "dxg": "FH",
      "odd_home_calc": 1.25,
      "odd_away_calc": 20,
      "entrada": "AWAY",
      "fthg": 4,
      "ftag": 0,
      "lp": -1
    },
    {
      "home": "M'gladbach",
      "away": "Schalke 04",
      "b365h": 2.15,
      "b365a": 3.3,
      "xgh": 1.78,
      "xga": 1.75,
      "dxg": "EQ",
      "odd_home_calc": 2.59,
      "odd_away_calc": 2.68,
      "entrada": "AWAY",
      "fthg": 3,
      "ftag": 1,
      "lp": -1
    },
    {
      "home": "Mainz",
      "away": "Stuttgart",
      "b365h": 2.05,
      "b365a": 3.5,
      "xgh": 1.13,
      "xga": 0.9,
      "dxg": "EQ",
      "odd_home_calc": 2.45,
      "odd_away_calc": 3.48,
      "entrada": "HOME",
      "fthg": 0,
      "ftag": 0,
      "lp": -1
    },
    {
      "home": "Werder Bremen",
      "away": "Hamburg",
      "b365h": 2.25,
      "b365a": 3.2,
      "xgh": 2.39,
      "xga": 0.48,
      "dxg": "FH",
      "odd_home_calc": 1.31,
      "odd_away_calc": 17.31,
      "entrada": "HOME",
      "fthg": 1,
      "ftag": 3,
      "lp": -1
    },
    {
      "home": "Augsburg",
      "away": "Mainz",
      "b365h": 2.3,
      "b365a": 3.1,
      "xgh": 1.31,
      "xga": 1.44,
      "dxg": "EQ",
      "odd_home_calc": 2.95,
      "odd_away_calc": 2.5,
      "entrada": "AWAY",
      "fthg": 3,
      "ftag": 3,
      "lp": -1
    },
    {
      "home": "Ein Frankfurt",
      "away": "Leverkusen",
      "b365h": 3.8,
      "b365a": 1.95,
      "xgh": 1.0,
      "xga": 2.65,
      "dxg": "FA",
      "odd_home_calc": 8.48,
      "odd_away_calc": 1.49,
      "entrada": "AWAY",
      "fthg": 1,
      "ftag": 3,
      "lp": 0.95
    },
    {
      "home": "Wolfsburg",
      "away": "Werder Bremen",
      "b365h": 1.57,
      "b365a": 5.75,
      "xgh": 2.64,
      "xga": 0.53,
      "dxg": "FH",
      "odd_home_calc": 1.3,
      "odd_away_calc": 18.7,
      "entrada": "HOME",
      "fthg": 6,
      "ftag": 0,
      "lp": 0.57
    },
    {
      "home": "Wolfsburg",
      "away": "Werder Bremen",
      "b365h": 1.57,
      "b365a": 5.75,
      "xgh": 3.26,
      "xga": 0.4,
      "dxg": "FH",
      "odd_home_calc": 1.26,
      "odd_away_calc": 20,
      "entrada": "HOME",
      "fthg": 6,
      "ftag": 0,
      "lp": 0.57
    },
    {
      "home": "Schalke 04",
      "away": "Bayern Munich",
      "b365h": 13.0,
      "b365a": 1.22,
      "xgh": 1.0,
      "xga": 2.91,
      "dxg": "FA",
      "odd_home_calc": 10.08,
      "odd_away_calc": 1.45,
      "entrada": "HOME",
      "fthg": 1,
      "ftag": 3,
      "lp": -1
    },
    {
      "home": "Leverkusen",
      "away": "M'gladbach",
      "b365h": 1.95,
      "b365a": 3.75,
      "xgh": 0.98,
      "xga": 0.75,
      "dxg": "EQ",
      "odd_home_calc": 2.51,
      "odd_away_calc": 3.74,
      "entrada": "HOME",
      "fthg": 5,
      "ftag": 0,
      "lp": 0.95
    },
    {
      "home": "Hamburg",
      "away": "Augsburg",
      "b365h": 2.4,
      "b365a": 3.0,
      "xgh": 0.93,
      "xga": 0.94,
      "dxg": "EQ",
      "odd_home_calc": 2.96,
      "odd_away_calc": 2.95,
      "entrada": "HOME",
      "fthg": 0,
      "ftag": 1,
      "lp": -1
    },
    {
      "home": "Werder Bremen",
      "away": "Hamburg",
      "b365h": 2.25,
      "b365a": 3.2,
      "xgh": 2.09,
      "xga": 0.7,
      "dxg": "FH",
      "odd_home_calc": 1.47,
      "odd_away_calc": 8.92,
      "entrada": "HOME",
      "fthg": 1,
      "ftag": 3,
      "lp": -1
    },
    {
      "home": "Augsburg",
      "away": "Wolfsburg",
      "b365h": 3.3,
      "b365a": 2.2,
      "xgh": 1.25,
      "xga": 1.2,
      "dxg": "EQ",
      "odd_home_calc": 2.66,
      "odd_away_calc": 2.87,
      "entrada": "HOME",
      "fthg": 0,
      "ftag": 0,
      "lp": -1
    },
    {
      "home": "Leverkusen",
      "away": "Schalke 04",
      "b365h": 1.62,
      "b365a": 5.25,
      "xgh": 2.26,
      "xga": 1.37,
      "dxg": "LH",
      "odd_home_calc": 1.83,
      "odd_away_calc": 4.48,
      "entrada": "AWAY",
      "fthg": 1,
      "ftag": 1,
      "lp": -1
    },
    {
      "home": "Ein Frankfurt",
      "away": "FC Koln",
      "b365h": 2.3,
      "b365a": 3.2,
      "xgh": 0.89,
      "xga": 0.78,
      "dxg": "EQ",
      "odd_home_calc": 2.78,
      "odd_away_calc": 3.37,
      "entrada": "HOME",
      "fthg": 6,
      "ftag": 2,
      "lp": 1.3
    },
    {
      "home": "Mainz",
      "away": "M'gladbach",
      "b365h": 2.6,
      "b365a": 2.7,
      "xgh": 0.95,
      "xga": 2.31,
      "dxg": "FA",
      "odd_home_calc": 7.16,
      "odd_away_calc": 1.54,
      "entrada": "AWAY",
      "fthg": 1,
      "ftag": 0,
      "lp": -1
    },
    {
      "home": "Werder Bremen",
      "away": "FC Koln",
      "b365h": 2.5,
      "b365a": 2.88,
      "xgh": 1.34,
      "xga": 0.17,
      "dxg": "FH",
      "odd_home_calc": 1.48,
      "odd_away_calc": 20,
      "entrada": "HOME",
      "fthg": 1,
      "ftag": 1,
      "lp": -1
    },
    {
      "home": "Leverkusen",
      "away": "M'gladbach",
      "b365h": 1.95,
      "b365a": 3.75,
      "xgh": 2.32,
      "xga": 0.68,
      "dxg": "FH",
      "odd_home_calc": 1.41,
      "odd_away_calc": 10.88,
      "entrada": "HOME",
      "fthg": 5,
      "ftag": 0,
      "lp": 0.95
    },
    {
      "home": "Darmstadt",
      "away": "Hertha",
      "b365h": 3.1,
      "b365a": 2.5,
      "xgh": 0.16,
      "xga": 4.0,
      "dxg": "FA",
      "odd_home_calc": 20,
      "odd_away_calc": 1.33,
      "entrada": "AWAY",
      "fthg": 0,
      "ftag": 4,
      "lp": 1.5
    },
    {
      "home": "Hoffenheim",
      "away": "Hannover",
      "b365h": 1.8,
      "b365a": 4.5,
      "xgh": 1.87,
      "xga": 0.72,
      "dxg": "FH",
      "odd_home_calc": 1.58,
      "odd_away_calc": 7.29,
      "entrada": "HOME",
      "fthg": 1,
      "ftag": 0,
      "lp": 0.8
    },
    {
      "home": "Ingolstadt",
      "away": "Mainz",
      "b365h": 2.4,
      "b365a": 3.1,
      "xgh": 0.89,
      "xga": 1.42,
      "dxg": "LA",
      "odd_home_calc": 4.23,
      "odd_away_calc": 2.04,
      "entrada": "AWAY",
      "fthg": 1,
      "ftag": 0,
      "lp": -1
    },
    {
      "home": "Schalke 04",
      "away": "Stuttgart",
      "b365h": 2.15,
      "b365a": 3.1,
      "xgh": 2.48,
      "xga": 0.86,
      "dxg": "FH",
      "odd_home_calc": 1.46,
      "odd_away_calc": 9.12,
      "entrada": "HOME",
      "fthg": 1,
      "ftag": 1,
      "lp": -1
    },
    {
      "home": "Schalke 04",
      "away": "Hoffenheim",
      "b365h": 1.67,
      "b365a": 5.0,
      "xgh": 1.47,
      "xga": 2.03,
      "dxg": "LA",
      "odd_home_calc": 3.62,
      "odd_away_calc": 2.05,
      "entrada": "AWAY",
      "fthg": 1,
      "ftag": 0,
      "lp": -1
    },
    {
      "home": "Ein Frankfurt",
      "away": "Werder Bremen",
      "b365h": 2.25,
      "b365a": 3.2,
      "xgh": 1.31,
      "xga": 1.83,
      "dxg": "LA",
      "odd_home_calc": 3.66,
      "odd_away_calc": 2.06,
      "entrada": "AWAY",
      "fthg": 2,
      "ftag": 1,
      "lp": -1
    },
    {
      "home": "FC Koln",
      "away": "Dortmund",
      "b365h": 7.0,
      "b365a": 1.44,
      "xgh": 0.07,
      "xga": 2.11,
      "dxg": "FA",
      "odd_home_calc": 20,
      "odd_away_calc": 1.19,
      "entrada": "AWAY",
      "fthg": 2,
      "ftag": 1,
      "lp": -1
    },
    {
      "home": "Hamburg",
      "away": "Augsburg",
      "b365h": 2.4,
      "b365a": 3.0,
      "xgh": 0.87,
      "xga": 0.94,
      "dxg": "EQ",
      "odd_home_calc": 3.16,
      "odd_away_calc": 2.82,
      "entrada": "HOME",
      "fthg": 0,
      "ftag": 1,
      "lp": -1
    },
    {
      "home": "Stuttgart",
      "away": "Wolfsburg",
      "b365h": 3.5,
      "b365a": 2.0,
      "xgh": 1.33,
      "xga": 1.4,
      "dxg": "EQ",
      "odd_home_calc": 2.82,
      "odd_away_calc": 2.61,
      "entrada": "HOME",
      "fthg": 3,
      "ftag": 1,
      "lp": 2.5
    },
    {
      "home": "Hertha",
      "away": "Mainz",
      "b365h": 2.15,
      "b365a": 3.4,
      "xgh": 1.34,
      "xga": 1.61,
      "dxg": "EQ",
      "odd_home_calc": 3.16,
      "odd_away_calc": 2.32,
      "entrada": "AWAY",
      "fthg": 2,
      "ftag": 0,
      "lp": -1
    },
    {
      "home": "Ingolstadt",
      "away": "FC Koln",
      "b365h": 2.5,
      "b365a": 3.0,
      "xgh": 1.41,
      "xga": 0.38,
      "dxg": "FH",
      "odd_home_calc": 1.59,
      "odd_away_calc": 10.16,
      "entrada": "HOME",
      "fthg": 1,
      "ftag": 1,
      "lp": -1
    },
    {
      "home": "Hoffenheim",
      "away": "Leverkusen",
      "b365h": 4.33,
      "b365a": 1.8,
      "xgh": 2.32,
      "xga": 1.18,
      "dxg": "FH",
      "odd_home_calc": 1.68,
      "odd_away_calc": 5.52,
      "entrada": "HOME",
      "fthg": 1,
      "ftag": 1,
      "lp": -1
    },
    {
      "home": "Ein Frankfurt",
      "away": "Mainz",
      "b365h": 2.88,
      "b365a": 2.5,
      "xgh": 2.47,
      "xga": 1.75,
      "dxg": "LH",
      "odd_home_calc": 2.0,
      "odd_away_calc": 3.82,
      "entrada": "HOME",
      "fthg": 2,
      "ftag": 1,
      "lp": 1.88
    },
    {
      "home": "Schalke 04",
      "away": "Werder Bremen",
      "b365h": 1.67,
      "b365a": 5.0,
      "xgh": 1.35,
      "xga": 0.91,
      "dxg": "LH",
      "odd_home_calc": 2.13,
      "odd_away_calc": 3.99,
      "entrada": "AWAY",
      "fthg": 1,
      "ftag": 3,
      "lp": 4.0
    },
    {
      "home": "Stuttgart",
      "away": "Hamburg",
      "b365h": 1.95,
      "b365a": 3.8,
      "xgh": 1.0,
      "xga": 0.96,
      "dxg": "EQ",
      "odd_home_calc": 2.84,
      "odd_away_calc": 2.99,
      "entrada": "AWAY",
      "fthg": 2,
      "ftag": 1,
      "lp": -1
    },
    {
      "home": "FC Koln",
      "away": "Hertha",
      "b365h": 2.1,
      "b365a": 3.75,
      "xgh": 0.98,
      "xga": 0.69,
      "dxg": "EQ",
      "odd_home_calc": 2.42,
      "odd_away_calc": 4.04,
      "entrada": "HOME",
      "fthg": 0,
      "ftag": 1,
      "lp": -1
    },
    {
      "home": "Darmstadt",
      "away": "Ingolstadt",
      "b365h": 2.55,
      "b365a": 2.88,
      "xgh": 1.97,
      "xga": 0.17,
      "dxg": "FH",
      "odd_home_calc": 1.25,
      "odd_away_calc": 20,
      "entrada": "HOME",
      "fthg": 2,
      "ftag": 0,
      "lp": 1.55
    },
    {
      "home": "Stuttgart",
      "away": "Hamburg",
      "b365h": 1.95,
      "b365a": 3.8,
      "xgh": 1.04,
      "xga": 0.96,
      "dxg": "EQ",
      "odd_home_calc": 2.73,
      "odd_away_calc": 3.08,
      "entrada": "AWAY",
      "fthg": 2,
      "ftag": 1,
      "lp": -1
    },
    {
      "home": "Hertha",
      "away": "Ein Frankfurt",
      "b365h": 1.85,
      "b365a": 4.33,
      "xgh": 1.01,
      "xga": 0.78,
      "dxg": "EQ",
      "odd_home_calc": 2.51,
      "odd_away_calc": 3.65,
      "entrada": "AWAY",
      "fthg": 2,
      "ftag": 0,
      "lp": -1
    },
    {
      "home": "Darmstadt",
      "away": "Dortmund",
      "b365h": 8.0,
      "b365a": 1.4,
      "xgh": 0.06,
      "xga": 1.71,
      "dxg": "FA",
      "odd_home_calc": 20,
      "odd_away_calc": 1.26,
      "entrada": "AWAY",
      "fthg": 0,
      "ftag": 2,
      "lp": 0.4
    },
    {
      "home": "Ingolstadt",
      "away": "Schalke 04",
      "b365h": 2.75,
      "b365a": 2.7,
      "xgh": 3.0,
      "xga": 0.91,
      "dxg": "FH",
      "odd_home_calc": 1.41,
      "odd_away_calc": 12.21,
      "entrada": "HOME",
      "fthg": 3,
      "ftag": 0,
      "lp": 1.75
    },
    {
      "home": "Hannover",
      "away": "Hamburg",
      "b365h": 3.1,
      "b365a": 2.38,
      "xgh": 0.87,
      "xga": 0.21,
      "dxg": "LH",
      "odd_home_calc": 1.97,
      "odd_away_calc": 11.53,
      "entrada": "HOME",
      "fthg": 0,
      "ftag": 3,
      "lp": -1
    },
    {
      "home": "Werder Bremen",
      "away": "Stuttgart",
      "b365h": 2.05,
      "b365a": 3.5,
      "xgh": 1.79,
      "xga": 0.78,
      "dxg": "FH",
      "odd_home_calc": 1.66,
      "odd_away_calc": 6.31,
      "entrada": "HOME",
      "fthg": 6,
      "ftag": 2,
      "lp": 1.05
    },
    {
      "home": "M'gladbach",
      "away": "FC Koln",
      "b365h": 1.91,
      "b365a": 4.0,
      "xgh": 1.7,
      "xga": 3.22,
      "dxg": "FA",
      "odd_home_calc": 5.96,
      "odd_away_calc": 1.76,
      "entrada": "AWAY",
      "fthg": 1,
      "ftag": 0,
      "lp": -1
    },
    {
      "home": "Hertha",
      "away": "Wolfsburg",
      "b365h": 2.75,
      "b365a": 2.6,
      "xgh": 1.43,
      "xga": 0.51,
      "dxg": "LH",
      "odd_home_calc": 1.68,
      "odd_away_calc": 7.67,
      "entrada": "HOME",
      "fthg": 1,
      "ftag": 1,
      "lp": -1
    },
    {
      "home": "FC Koln",
      "away": "Ein Frankfurt",
      "b365h": 1.91,
      "b365a": 3.8,
      "xgh": 0.53,
      "xga": 1.15,
      "dxg": "LA",
      "odd_home_calc": 5.9,
      "odd_away_calc": 1.96,
      "entrada": "AWAY",
      "fthg": 3,
      "ftag": 1,
      "lp": -1
    },
    {
      "home": "Werder Bremen",
      "away": "Hoffenheim",
      "b365h": 2.2,
      "b365a": 3.25,
      "xgh": 2.02,
      "xga": 1.07,
      "dxg": "LH",
      "odd_home_calc": 1.73,
      "odd_away_calc": 5.17,
      "entrada": "HOME",
      "fthg": 1,
      "ftag": 1,
      "lp": -1
    },
    {
      "home": "Mainz",
      "away": "Schalke 04",
      "b365h": 2.9,
      "b365a": 2.45,
      "xgh": 0.53,
      "xga": 1.02,
      "dxg": "LA",
      "odd_home_calc": 5.36,
      "odd_away_calc": 2.13,
      "entrada": "AWAY",
      "fthg": 2,
      "ftag": 1,
      "lp": -1
    },
    {
      "home": "Hoffenheim",
      "away": "Mainz",
      "b365h": 2.4,
      "b365a": 2.9,
      "xgh": 0.9,
      "xga": 0.9,
      "dxg": "EQ",
      "odd_home_calc": 3.0,
      "odd_away_calc": 2.98,
      "entrada": "HOME",
      "fthg": 3,
      "ftag": 2,
      "lp": 1.4
    },
    {
      "home": "M'gladbach",
      "away": "FC Koln",
      "b365h": 1.91,
      "b365a": 4.0,
      "xgh": 1.63,
      "xga": 1.63,
      "dxg": "EQ",
      "odd_home_calc": 2.66,
      "odd_away_calc": 2.64,
      "entrada": "AWAY",
      "fthg": 1,
      "ftag": 0,
      "lp": -1
    },
    {
      "home": "Hertha",
      "away": "Wolfsburg",
      "b365h": 2.75,
      "b365a": 2.6,
      "xgh": 1.27,
      "xga": 0.58,
      "dxg": "LH",
      "odd_home_calc": 1.88,
      "odd_away_calc": 5.9,
      "entrada": "HOME",
      "fthg": 1,
      "ftag": 1,
      "lp": -1
    },
    {
      "home": "Schalke 04",
      "away": "Stuttgart",
      "b365h": 2.15,
      "b365a": 3.1,
      "xgh": 1.82,
      "xga": 0.87,
      "dxg": "LH",
      "odd_home_calc": 1.7,
      "odd_away_calc": 5.72,
      "entrada": "HOME",
      "fthg": 1,
      "ftag": 1,
      "lp": -1
    },
    {
      "home": "Hannover",
      "away": "Augsburg",
      "b365h": 2.63,
      "b365a": 2.75,
      "xgh": 2.36,
      "xga": 1.57,
      "dxg": "LH",
      "odd_home_calc": 1.93,
      "odd_away_calc": 4.04,
      "entrada": "HOME",
      "fthg": 0,
      "ftag": 1,
      "lp": -1
    },
    {
      "home": "Leverkusen",
      "away": "Dortmund",
      "b365h": 3.4,
      "b365a": 2.1,
      "xgh": 1.97,
      "xga": 1.47,
      "dxg": "LH",
      "odd_home_calc": 2.09,
      "odd_away_calc": 3.52,
      "entrada": "HOME",
      "fthg": 0,
      "ftag": 1,
      "lp": -1
    },
    {
      "home": "FC Koln",
      "away": "Hertha",
      "b365h": 2.1,
      "b365a": 3.75,
      "xgh": 0.69,
      "xga": 0.71,
      "dxg": "EQ",
      "odd_home_calc": 3.3,
      "odd_away_calc": 3.18,
      "entrada": "AWAY",
      "fthg": 0,
      "ftag": 1,
      "lp": 2.75
    },
    {
      "home": "Augsburg",
      "away": "M'gladbach",
      "b365h": 2.7,
      "b365a": 2.6,
      "xgh": 0.5,
      "xga": 1.16,
      "dxg": "LA",
      "odd_home_calc": 6.22,
      "odd_away_calc": 1.92,
      "entrada": "AWAY",
      "fthg": 2,
      "ftag": 2,
      "lp": -1
    },
    {
      "home": "Ein Frankfurt",
      "away": "Schalke 04",
      "b365h": 3.2,
      "b365a": 2.25,
      "xgh": 0.96,
      "xga": 0.44,
      "dxg": "LH",
      "odd_home_calc": 2.13,
      "odd_away_calc": 5.99,
      "entrada": "HOME",
      "fthg": 0,
      "ftag": 0,
      "lp": -1
    },
    {
      "home": "Hoffenheim",
      "away": "FC Koln",
      "b365h": 2.38,
      "b365a": 3.1,
      "xgh": 0.85,
      "xga": 0.81,
      "dxg": "EQ",
      "odd_home_calc": 2.96,
      "odd_away_calc": 3.16,
      "entrada": "HOME",
      "fthg": 1,
      "ftag": 1,
      "lp": -1
    },
    {
      "home": "M'gladbach",
      "away": "Hertha",
      "b365h": 1.83,
      "b365a": 4.33,
      "xgh": 2.88,
      "xga": 0.55,
      "dxg": "FH",
      "odd_home_calc": 1.29,
      "odd_away_calc": 20,
      "entrada": "HOME",
      "fthg": 5,
      "ftag": 0,
      "lp": 0.83
    },
    {
      "home": "Leverkusen",
      "away": "Hamburg",
      "b365h": 1.67,
      "b365a": 5.5,
      "xgh": 1.9,
      "xga": 0.35,
      "dxg": "FH",
      "odd_home_calc": 1.35,
      "odd_away_calc": 16.82,
      "entrada": "HOME",
      "fthg": 1,
      "ftag": 0,
      "lp": 0.67
    },
    {
      "home": "Ein Frankfurt",
      "away": "Hannover",
      "b365h": 1.85,
      "b365a": 4.33,
      "xgh": 1.18,
      "xga": 0.12,
      "dxg": "FH",
      "odd_home_calc": 1.54,
      "odd_away_calc": 20,
      "entrada": "HOME",
      "fthg": 1,
      "ftag": 0,
      "lp": 0.85
    },
    {
      "home": "Wolfsburg",
      "away": "Darmstadt",
      "b365h": 1.44,
      "b365a": 8.0,
      "xgh": 0.98,
      "xga": 0.97,
      "dxg": "EQ",
      "odd_home_calc": 2.89,
      "odd_away_calc": 2.94,
      "entrada": "AWAY",
      "fthg": 1,
      "ftag": 1,
      "lp": -1
    },
    {
      "home": "Augsburg",
      "away": "Stuttgart",
      "b365h": 2.45,
      "b365a": 2.75,
      "xgh": 1.18,
      "xga": 1.06,
      "dxg": "EQ",
      "odd_home_calc": 2.59,
      "odd_away_calc": 3.09,
      "entrada": "HOME",
      "fthg": 1,
      "ftag": 0,
      "lp": 1.45
    },
    {
      "home": "Werder Bremen",
      "away": "Mainz",
      "b365h": 2.38,
      "b365a": 3.0,
      "xgh": 1.69,
      "xga": 1.4,
      "dxg": "EQ",
      "odd_home_calc": 2.29,
      "odd_away_calc": 3.17,
      "entrada": "HOME",
      "fthg": 1,
      "ftag": 1,
      "lp": -1
    },
    {
      "home": "Wolfsburg",
      "away": "Darmstadt",
      "b365h": 1.44,
      "b365a": 8.0,
      "xgh": 0.99,
      "xga": 0.98,
      "dxg": "EQ",
      "odd_home_calc": 2.9,
      "odd_away_calc": 2.91,
      "entrada": "AWAY",
      "fthg": 1,
      "ftag": 1,
      "lp": -1
    },
    {
      "home": "Stuttgart",
      "away": "Leverkusen",
      "b365h": 2.3,
      "b365a": 2.9,
      "xgh": 1.36,
      "xga": 1.82,
      "dxg": "LA",
      "odd_home_calc": 3.5,
      "odd_away_calc": 2.12,
      "entrada": "AWAY",
      "fthg": 0,
      "ftag": 2,
      "lp": 1.9
    },
    {
      "home": "Augsburg",
      "away": "Dortmund",
      "b365h": 6.5,
      "b365a": 1.5,
      "xgh": 1.0,
      "xga": 1.15,
      "dxg": "EQ",
      "odd_home_calc": 3.18,
      "odd_away_calc": 2.57,
      "entrada": "HOME",
      "fthg": 1,
      "ftag": 3,
      "lp": -1
    },
    {
      "home": "Hannover",
      "away": "M'gladbach",
      "b365h": 5.5,
      "b365a": 1.62,
      "xgh": 1.42,
      "xga": 0.31,
      "dxg": "FH",
      "odd_home_calc": 1.53,
      "odd_away_calc": 12.79,
      "entrada": "HOME",
      "fthg": 2,
      "ftag": 0,
      "lp": 4.5
    },
    {
      "home": "Hamburg",
      "away": "FC Koln",
      "b365h": 2.5,
      "b365a": 3.0,
      "xgh": 0.2,
      "xga": 0.58,
      "dxg": "LA",
      "odd_home_calc": 9.34,
      "odd_away_calc": 2.63,
      "entrada": "AWAY",
      "fthg": 1,
      "ftag": 1,
      "lp": -1
    },
    {
      "home": "Ein Frankfurt",
      "away": "Hoffenheim",
      "b365h": 2.3,
      "b365a": 3.1,
      "xgh": 1.32,
      "xga": 1.41,
      "dxg": "EQ",
      "odd_home_calc": 2.85,
      "odd_away_calc": 2.58,
      "entrada": "AWAY",
      "fthg": 0,
      "ftag": 2,
      "lp": 2.1
    },
    {
      "home": "Werder Bremen",
      "away": "Wolfsburg",
      "b365h": 2.5,
      "b365a": 2.75,
      "xgh": 1.06,
      "xga": 0.65,
      "dxg": "LH",
      "odd_home_calc": 2.23,
      "odd_away_calc": 4.5,
      "entrada": "HOME",
      "fthg": 3,
      "ftag": 2,
      "lp": 1.5
    },
    {
      "home": "Dortmund",
      "away": "Hamburg",
      "b365h": 1.33,
      "b365a": 9.0,
      "xgh": 2.48,
      "xga": 2.02,
      "dxg": "LH",
      "odd_home_calc": 2.23,
      "odd_away_calc": 3.28,
      "entrada": "AWAY",
      "fthg": 3,
      "ftag": 0,
      "lp": -1
    },
    {
      "home": "Darmstadt",
      "away": "Ein Frankfurt",
      "b365h": 2.5,
      "b365a": 3.0,
      "xgh": 2.05,
      "xga": 1.16,
      "dxg": "LH",
      "odd_home_calc": 1.78,
      "odd_away_calc": 4.8,
      "entrada": "HOME",
      "fthg": 1,
      "ftag": 2,
      "lp": -1
    },
    {
      "home": "Schalke 04",
      "away": "Leverkusen",
      "b365h": 3.0,
      "b365a": 2.4,
      "xgh": 1.08,
      "xga": 1.3,
      "dxg": "EQ",
      "odd_home_calc": 3.24,
      "odd_away_calc": 2.43,
      "entrada": "AWAY",
      "fthg": 2,
      "ftag": 3,
      "lp": 1.4
    },
    {
      "home": "Ein Frankfurt",
      "away": "Mainz",
      "b365h": 2.88,
      "b365a": 2.5,
      "xgh": 2.31,
      "xga": 1.48,
      "dxg": "LH",
      "odd_home_calc": 1.88,
      "odd_away_calc": 4.23,
      "entrada": "HOME",
      "fthg": 2,
      "ftag": 1,
      "lp": 1.88
    },
    {
      "home": "Hamburg",
      "away": "Hertha",
      "b365h": 2.88,
      "b365a": 2.63,
      "xgh": 2.43,
      "xga": 0.19,
      "dxg": "FH",
      "odd_home_calc": 1.2,
      "odd_away_calc": 20,
      "entrada": "HOME",
      "fthg": 2,
      "ftag": 0,
      "lp": 1.88
    },
    {
      "home": "Darmstadt",
      "away": "Ein Frankfurt",
      "b365h": 2.5,
      "b365a": 3.0,
      "xgh": 1.61,
      "xga": 1.23,
      "dxg": "LH",
      "odd_home_calc": 2.18,
      "odd_away_calc": 3.46,
      "entrada": "HOME",
      "fthg": 1,
      "ftag": 2,
      "lp": -1
    },
    {
      "home": "Hoffenheim",
      "away": "Ingolstadt",
      "b365h": 1.8,
      "b365a": 4.6,
      "xgh": 1.76,
      "xga": 0.31,
      "dxg": "FH",
      "odd_home_calc": 1.38,
      "odd_away_calc": 16.69,
      "entrada": "HOME",
      "fthg": 2,
      "ftag": 1,
      "lp": 0.8
    },
    {
      "home": "M'gladbach",
      "away": "Werder Bremen",
      "b365h": 1.7,
      "b365a": 4.5,
      "xgh": 1.79,
      "xga": 0.61,
      "dxg": "FH",
      "odd_home_calc": 1.54,
      "odd_away_calc": 8.26,
      "entrada": "HOME",
      "fthg": 5,
      "ftag": 1,
      "lp": 0.7
    },
    {
      "home": "Dortmund",
      "away": "Bayern Munich",
      "b365h": 3.1,
      "b365a": 2.3,
      "xgh": 0.38,
      "xga": 0.95,
      "dxg": "LA",
      "odd_home_calc": 6.98,
      "odd_away_calc": 2.05,
      "entrada": "AWAY",
      "fthg": 0,
      "ftag": 0,
      "lp": -1
    },
    {
      "home": "Wolfsburg",
      "away": "Stuttgart",
      "b365h": 2.3,
      "b365a": 2.75,
      "xgh": 3.04,
      "xga": 0.79,
      "dxg": "FH",
      "odd_home_calc": 1.37,
      "odd_away_calc": 15.21,
      "entrada": "HOME",
      "fthg": 3,
      "ftag": 1,
      "lp": 1.3
    },
    {
      "home": "Werder Bremen",
      "away": "Hannover",
      "b365h": 1.73,
      "b365a": 4.75,
      "xgh": 2.86,
      "xga": 0.86,
      "dxg": "FH",
      "odd_home_calc": 1.4,
      "odd_away_calc": 11.89,
      "entrada": "HOME",
      "fthg": 4,
      "ftag": 1,
      "lp": 0.73
    },
    {
      "home": "Ein Frankfurt",
      "away": "Ingolstadt",
      "b365h": 2.5,
      "b365a": 3.0,
      "xgh": 1.0,
      "xga": 0.17,
      "dxg": "LH",
      "odd_home_calc": 1.74,
      "odd_away_calc": 16.4,
      "entrada": "HOME",
      "fthg": 1,
      "ftag": 1,
      "lp": -1
    },
    {
      "home": "Wolfsburg",
      "away": "M'gladbach",
      "b365h": 1.95,
      "b365a": 3.6,
      "xgh": 1.72,
      "xga": 0.7,
      "dxg": "FH",
      "odd_home_calc": 1.64,
      "odd_away_calc": 6.71,
      "entrada": "HOME",
      "fthg": 2,
      "ftag": 1,
      "lp": 0.95
    },
    {
      "home": "Hoffenheim",
      "away": "Schalke 04",
      "b365h": 3.2,
      "b365a": 2.05,
      "xgh": 0.62,
      "xga": 0.24,
      "dxg": "LH",
      "odd_home_calc": 2.6,
      "odd_away_calc": 7.96,
      "entrada": "HOME",
      "fthg": 1,
      "ftag": 4,
      "lp": -1
    },
    {
      "home": "Hamburg",
      "away": "FC Koln",
      "b365h": 2.5,
      "b365a": 3.0,
      "xgh": 0.33,
      "xga": 0.64,
      "dxg": "LA",
      "odd_home_calc": 6.15,
      "odd_away_calc": 2.69,
      "entrada": "AWAY",
      "fthg": 1,
      "ftag": 1,
      "lp": -1
    },
    {
      "home": "Hoffenheim",
      "away": "Schalke 04",
      "b365h": 3.2,
      "b365a": 2.05,
      "xgh": 0.69,
      "xga": 1.43,
      "dxg": "LA",
      "odd_home_calc": 5.55,
      "odd_away_calc": 1.83,
      "entrada": "AWAY",
      "fthg": 1,
      "ftag": 4,
      "lp": 1.05
    },
    {
      "home": "Werder Bremen",
      "away": "Ein Frankfurt",
      "b365h": 2.0,
      "b365a": 3.5,
      "xgh": 2.03,
      "xga": 0.75,
      "dxg": "FH",
      "odd_home_calc": 1.52,
      "odd_away_calc": 7.89,
      "entrada": "HOME",
      "fthg": 1,
      "ftag": 0,
      "lp": 1.0
    },
    {
      "home": "Wolfsburg",
      "away": "Stuttgart",
      "b365h": 2.3,
      "b365a": 2.75,
      "xgh": 3.02,
      "xga": 0.82,
      "dxg": "FH",
      "odd_home_calc": 1.38,
      "odd_away_calc": 14.27,
      "entrada": "HOME",
      "fthg": 3,
      "ftag": 1,
      "lp": 1.3
    },
    {
      "home": "Hamburg",
      "away": "Darmstadt",
      "b365h": 2.05,
      "b365a": 3.6,
      "xgh": 0.99,
      "xga": 1.98,
      "dxg": "LA",
      "odd_home_calc": 5.46,
      "odd_away_calc": 1.7,
      "entrada": "AWAY",
      "fthg": 1,
      "ftag": 2,
      "lp": 2.6
    },
    {
      "home": "Ingolstadt",
      "away": "Augsburg",
      "b365h": 2.5,
      "b365a": 3.1,
      "xgh": 1.29,
      "xga": 0.76,
      "dxg": "LH",
      "odd_home_calc": 2.06,
      "odd_away_calc": 4.52,
      "entrada": "HOME",
      "fthg": 2,
      "ftag": 1,
      "lp": 1.5
    },
    {
      "home": "Hannover",
      "away": "Mainz",
      "b365h": 2.75,
      "b365a": 2.6,
      "xgh": 1.48,
      "xga": 1.33,
      "dxg": "EQ",
      "odd_home_calc": 2.49,
      "odd_away_calc": 2.94,
      "entrada": "HOME",
      "fthg": 0,
      "ftag": 1,
      "lp": -1
    },
    {
      "home": "Ein Frankfurt",
      "away": "Stuttgart",
      "b365h": 2.7,
      "b365a": 2.5,
      "xgh": 2.3,
      "xga": 0.75,
      "dxg": "FH",
      "odd_home_calc": 1.44,
      "odd_away_calc": 9.52,
      "entrada": "HOME",
      "fthg": 2,
      "ftag": 4,
      "lp": -1
    },
    {
      "home": "Hamburg",
      "away": "FC Koln",
      "b365h": 2.5,
      "b365a": 3.0,
      "xgh": 0.42,
      "xga": 0.68,
      "dxg": "EQ",
      "odd_home_calc": 5.08,
      "odd_away_calc": 2.72,
      "entrada": "AWAY",
      "fthg": 1,
      "ftag": 1,
      "lp": -1
    },
    {
      "home": "Hoffenheim",
      "away": "Darmstadt",
      "b365h": 2.0,
      "b365a": 4.0,
      "xgh": 2.2,
      "xga": 0.99,
      "dxg": "FH",
      "odd_home_calc": 1.6,
      "odd_away_calc": 6.38,
      "entrada": "HOME",
      "fthg": 0,
      "ftag": 2,
      "lp": -1
    },
    {
      "home": "Stuttgart",
      "away": "Mainz",
      "b365h": 2.1,
      "b365a": 3.2,
      "xgh": 1.23,
      "xga": 1.54,
      "dxg": "LA",
      "odd_home_calc": 3.32,
      "odd_away_calc": 2.27,
      "entrada": "AWAY",
      "fthg": 1,
      "ftag": 3,
      "lp": 2.2
    },
    {
      "home": "FC Koln",
      "away": "Werder Bremen",
      "b365h": 2.8,
      "b365a": 2.38,
      "xgh": 0.5,
      "xga": 1.4,
      "dxg": "LA",
      "odd_home_calc": 7.63,
      "odd_away_calc": 1.69,
      "entrada": "AWAY",
      "fthg": 0,
      "ftag": 0,
      "lp": -1
    },
    {
      "home": "Hamburg",
      "away": "Wolfsburg",
      "b365h": 2.7,
      "b365a": 2.63,
      "xgh": 1.38,
      "xga": 0.62,
      "dxg": "LH",
      "odd_home_calc": 1.82,
      "odd_away_calc": 5.95,
      "entrada": "HOME",
      "fthg": 0,
      "ftag": 1,
      "lp": -1
    },
    {
      "home": "Ingolstadt",
      "away": "Bayern Munich",
      "b365h": 15.0,
      "b365a": 1.18,
      "xgh": 1.0,
      "xga": 1.33,
      "dxg": "LA",
      "odd_home_calc": 3.57,
      "odd_away_calc": 2.27,
      "entrada": "HOME",
      "fthg": 1,
      "ftag": 2,
      "lp": -1
    },
    {
      "home": "Ein Frankfurt",
      "away": "Hoffenheim",
      "b365h": 2.3,
      "b365a": 3.1,
      "xgh": 1.18,
      "xga": 1.44,
      "dxg": "EQ",
      "odd_home_calc": 3.25,
      "odd_away_calc": 2.34,
      "entrada": "AWAY",
      "fthg": 0,
      "ftag": 2,
      "lp": 2.1
    },
    {
      "home": "Hamburg",
      "away": "Darmstadt",
      "b365h": 2.05,
      "b365a": 3.6,
      "xgh": 0.99,
      "xga": 1.99,
      "dxg": "LA",
      "odd_home_calc": 5.5,
      "odd_away_calc": 1.7,
      "entrada": "AWAY",
      "fthg": 1,
      "ftag": 2,
      "lp": 2.6
    },
    {
      "home": "Stuttgart",
      "away": "Bayern Munich",
      "b365h": 6.0,
      "b365a": 1.5,
      "xgh": 1.96,
      "xga": 1.26,
      "dxg": "LH",
      "odd_home_calc": 1.92,
      "odd_away_calc": 4.11,
      "entrada": "HOME",
      "fthg": 1,
      "ftag": 3,
      "lp": -1
    },
    {
      "home": "Werder Bremen",
      "away": "Augsburg",
      "b365h": 2.05,
      "b365a": 3.5,
      "xgh": 1.93,
      "xga": 0.84,
      "dxg": "FH",
      "odd_home_calc": 1.63,
      "odd_away_calc": 6.37,
      "entrada": "HOME",
      "fthg": 1,
      "ftag": 2,
      "lp": -1
    },
    {
      "home": "Wolfsburg",
      "away": "Mainz",
      "b365h": 2.2,
      "b365a": 3.25,
      "xgh": 0.95,
      "xga": 1.74,
      "dxg": "LA",
      "odd_home_calc": 4.89,
      "odd_away_calc": 1.82,
      "entrada": "AWAY",
      "fthg": 1,
      "ftag": 1,
      "lp": -1
    },
    {
      "home": "Hertha",
      "away": "Schalke 04",
      "b365h": 2.4,
      "b365a": 3.0,
      "xgh": 0.68,
      "xga": 0.84,
      "dxg": "EQ",
      "odd_home_calc": 3.69,
      "odd_away_calc": 2.73,
      "entrada": "HOME",
      "fthg": 2,
      "ftag": 0,
      "lp": 1.4
    },
    {
      "home": "Darmstadt",
      "away": "Augsburg",
      "b365h": 2.8,
      "b365a": 2.7,
      "xgh": 0.18,
      "xga": 1.59,
      "dxg": "FA",
      "odd_home_calc": 20,
      "odd_away_calc": 1.37,
      "entrada": "AWAY",
      "fthg": 2,
      "ftag": 2,
      "lp": -1
    },
    {
      "home": "Hannover",
      "away": "FC Koln",
      "b365h": 3.5,
      "b365a": 2.15,
      "xgh": 0.48,
      "xga": 2.0,
      "dxg": "FA",
      "odd_home_calc": 12.71,
      "odd_away_calc": 1.39,
      "entrada": "AWAY",
      "fthg": 0,
      "ftag": 2,
      "lp": 1.15
    },
    {
      "home": "Hannover",
      "away": "FC Koln",
      "b365h": 3.5,
      "b365a": 2.15,
      "xgh": 0.36,
      "xga": 2.0,
      "dxg": "FA",
      "odd_home_calc": 17.62,
      "odd_away_calc": 1.33,
      "entrada": "AWAY",
      "fthg": 0,
      "ftag": 2,
      "lp": 1.15
    }
  ],
  "lucro_total": 17.589999999999996,
  "acertos": 65,
  "erros": 92,
  "total_jogos": 306,
  "completo": true
}